Workbook

Sheet American journal voucher
G1: =H2-G2 -> 59799 | I1: =J2-I2 -> 388408 | K1: =L2-K2 -> -34124.8 | M1: =N2-M2 -> 1087750 | O1: =O2-P2 -> 23305332 | Q1: =R2-Q2 -> 3154668 | S1: =T2-S2 -> 3309592 | U1: =V2-U2 -> 1832308 | W1: =X2-W2 -> 54895 | Y1: =Y2-Z2 -> 5579853 | AA1: =AB2-AA2 -> 0 | AC1: =AC2-AD2 -> 0 | AE1: =AE2-AF2 -> 0 | AG1: =AH2-AG2 -> 0 | AI1: =AJ2-AI2 -> 0 | AK1: =AL2-AK2 -> -4483795.9 | AM1: =AN2-AM2 -> 326070 | AO1: =AP2-AO2 -> 1170982 | AQ1: =AR2-AQ2 -> 4090461.8 | AS1: =AT2-AS2 -> 8786830 | AW1: =AX2-AW2 -> 5121874.9 | AY1: =AZ2-AY2 -> 944383 | BA1: =BA2-BB2 -> 0 | BC1: =BD2-BC2 -> 5863798.8 | BE1: =BF2-BE2 -> 0 | BG1: =BH2-BG2 -> 0 | BI1: =BJ2-BI2 -> 0 | BK1: =BK2-BL2 -> 0 | BM1: =BN2-BM2 -> 0 | BO1: =BO2-BP2 -> 0 | BQ1: =BR2-BQ2 -> -700 | BS1: =BT2-BS2 -> 755676
E2: =SUBTOTAL(9,E5:E5097) -> 1.9928317e+08 | F2: =SUBTOTAL(9,F5:F5097) -> 1.9928317e+08 | G2: =SUBTOTAL(9,G5:G5097) -> 5066015 | H2: =SUBTOTAL(9,H5:H5097) -> 5125814 | I2: =SUBTOTAL(9,I5:I5097) -> 0 | J2: =SUBTOTAL(9,J5:J5097) -> 388408 | K2: =SUBTOTAL(9,K5:K5097) -> 301199.8 | L2: =SUBTOTAL(9,L5:L5097) -> 267075 | ... CF2: =SUBTOTAL(9,CF5:CF5097) -> 0
A3: Ref | B3: Date | C3: Description | D3: Net | E3: Total | G3: Cash | I3: Bank | K3: Vodafon Cash | M3: Inventory | O3: Sales | Q3: Instapay 2 | S3: Paymob | U3: Value | W3: Gift Card | Y3: Share holder's | AA3: Depreciation | AC3: Capital | AE3: Retained earning | AG3: Prepared Expenses | AI3: Fixed assets | AK3: Opreation | AM3: Shipping | AO3: Administrative Expenses | AQ3: Advance to employees | AS3: Cost | AU3: Purchasing | AW3: Discount | AY3: Refund | BA3: Suppliers | BC3: Markting | BE3: Bank Masr | BG3: Bank interest | BI3: other Ep | BK3: Bank interest cr | BM3: p&l | BO3: deposits revenue | BQ3: سلف | BS3: SYMPL | BU3: INSTAPAY
E4: Credit | F4: Debit | G4: Credit | H4: Debit | I4: Credit | J4: Debit | K4: Credit | L4: Debit | M4: Credit | N4: Debit | O4: Credit | P4: Debit | Q4: Credit | R4: Debit | S4: Credit | T4: Debit | U4: Credit | V4: Debit | W4: Credit | X4: Debit | Y4: Credit | Z4: Debit | AA4: Credit | AB4: Debit | AC4: Credit | AD4: Debit | AE4: Credit | AF4: Debit | AG4: Credit | AH4: Debit | AI4: Credit | AJ4: Debit | AK4: Credit | AL4: Debit | AM4: Credit | AN4: Debit | AO4: Credit | AP4: Debit | AQ4: Credit | AR4: Debit | AS4: Credit | AT4: Debit | AU4: Credit | AV4: Debit | AW4: Credit | AX4: Debit | AY4: Credit | AZ4: Debit | BA4: Credit | BB4: Debit | BC4: Credit | BD4: Debit | BE4: Credit | BF4: Debit | BG4: Credit | BH4: Debit | BI4: Credit | BJ4: Debit | BK4: Credit | BL4: Debit | BM4: Credit | BN4: Debit | BO4: credit | BP4: Debit | BQ4: credit | BR4: Debit | BS4: Credit | BT4: Debit | BU4: Credit | BV4: Debit | BW4: credit | BX4: Debit | BY4: Credit | BZ4: Debit | CA4: Credit | CB4: Debit | CC4: Credit | CD4: Debit | CE4: Credit | CF4: Debit
B5: 0 | C5: op | D5: =F5-E5 -> 0 | E5: =G5+I5+CC266+K5+M5+O5+Q5+S5+U5+W5+Y5+AA5+AC5+AE5+AG5+AI5+AK5+AM5+AO5+AQ5+AS5+AU5+AW5+AY5+BA5+BC5+BE5+BG5+BI5+BK5+BM5+BO5+BQ5+BS5+BU5+BW5+BY5+CA5+CE266 -> 0 | F5: =H5+J5+L5+CD266+N5+P5+R5+T5+V5+X5+Z5+AB5+AD5+AF5+AH5+AJ5+AL5+AN5+AP5+AR5+AT5+AV5+AX5+AZ5+BB5+BD5+BF5+BH5+BJ5+BL5+BN5+BP5+BR5+BT5+BV5+BX5+BZ5+CB5+CF266 -> 0
A6: 1 | B6: 46023 | C6: Sales | D6: =F6-E6 -> 0 | E6: =G6+I6+CC267+K6+M6+O6+Q6+S6+U6+W6+Y6+AA6+AC6+AE6+AG6+AI6+AK6+AM6+AO6+AQ6+AS6+AU6+AW6+AY6+BA6+BC6+BE6+BG6+BI6+BK6+BM6+BO6+BQ6+BS6+BU6+BW6+BY6+CA6+CE267 -> 552915 | F6: =H6+J6+L6+CD267+N6+P6+R6+T6+V6+X6+Z6+AB6+AD6+AF6+AH6+AJ6+AL6+AN6+AP6+AR6+AT6+AV6+AX6+AZ6+BB6+BD6+BF6+BH6+BJ6+BL6+BN6+BP6+BR6+BT6+BV6+BX6+BZ6+CB6+CF267 -> 552915 | O6: 509471 | AK6: 43444 | AL6: 509471 | AX6: 43444
A7: 2 | B7: 46023 | C7: Returns | D7: =F7-E7 -> 0 | E7: =G7+I7+CC268+K7+M7+O7+Q7+S7+U7+W7+Y7+AA7+AC7+AE7+AG7+AI7+AK7+AM7+AO7+AQ7+AS7+AU7+AW7+AY7+BA7+BC7+BE7+BG7+BI7+BK7+BM7+BO7+BQ7+BS7+BU7+BW7+BY7+CA7+CE268 -> 296659 | F7: =H7+J7+L7+CD268+N7+P7+R7+T7+V7+X7+Z7+AB7+AD7+AF7+AH7+AJ7+AL7+AN7+AP7+AR7+AT7+AV7+AX7+AZ7+BB7+BD7+BF7+BH7+BJ7+BL7+BN7+BP7+BR7+BT7+BV7+BX7+BZ7+CB7+CF268 -> 296659 | P7: 296659 | AQ7: 296659
A8: 3 | B8: 46023 | C8: Returns Cost | D8: =F8-E8 -> 0 | E8: =G8+I8+CC269+K8+M8+O8+Q8+S8+U8+W8+Y8+AA8+AC8+AE8+AG8+AI8+AK8+AM8+AO8+AQ8+AS8+AU8+AW8+AY8+BA8+BC8+BE8+BG8+BI8+BK8+BM8+BO8+BQ8+BS8+BU8+BW8+BY8+CA8+CE269 -> 144100 | F8: =H8+J8+L8+CD269+N8+P8+R8+T8+V8+X8+Z8+AB8+AD8+AF8+AH8+AJ8+AL8+AN8+AP8+AR8+AT8+AV8+AX8+AZ8+BB8+BD8+BF8+BH8+BJ8+BL8+BN8+BP8+BR8+BT8+BV8+BX8+BZ8+CB8+CF269 -> 144100 | N8: 144100 | AS8: 144100
A9: 4 | B9: 46023 | C9: Cost | D9: =F9-E9 -> 0 | E9: =G9+I9+CC270+K9+M9+O9+Q9+S9+U9+W9+Y9+AA9+AC9+AE9+AG9+AI9+AK9+AM9+AO9+AQ9+AS9+AU9+AW9+AY9+BA9+BC9+BE9+BG9+BI9+BK9+BM9+BO9+BQ9+BS9+BU9+BW9+BY9+CA9+CE270 -> 220600 | F9: =H9+J9+L9+CD270+N9+P9+R9+T9+V9+X9+Z9+AB9+AD9+AF9+AH9+AJ9+AL9+AN9+AP9+AR9+AT9+AV9+AX9+AZ9+BB9+BD9+BF9+BH9+BJ9+BL9+BN9+BP9+BR9+BT9+BV9+BX9+BZ9+CB9+CF270 -> 220600 | M9: 220600 | AT9: 220600
A10: 5 | B10: 46023 | C10: Shipping | D10: =F10-E10 -> 0 | E10: =G10+I10+CC271+K10+M10+O10+Q10+S10+U10+W10+Y10+AA10+AC10+AE10+AG10+AI10+AK10+AM10+AO10+AQ10+AS10+AU10+AW10+AY10+BA10+BC10+BE10+BG10+BI10+BK10+BM10+BO10+BQ10+BS10+BU10+BW10+BY10+CA10+CE271 -> 3140 | F10: =H10+J10+L10+CD271+N10+P10+R10+T10+V10+X10+Z10+AB10+AD10+AF10+AH10+AJ10+AL10+AN10+AP10+AR10+AT10+AV10+AX10+AZ10+BB10+BD10+BF10+BH10+BJ10+BL10+BN10+BP10+BR10+BT10+BV10+BX10+BZ10+CB10+CF271 -> 3140 | G10: 3140 | AN10: 3140
A11: 6 | B11: 46023 | C11: Pickup | D11: =F11-E11 -> 0 | E11: =G11+I11+CC276+K11+M11+O11+Q11+S11+U11+W11+Y11+AA11+AC11+AE11+AG11+AI11+AK11+AM11+AO11+AQ11+AS11+AU11+AW11+AY11+BA11+BC11+BE11+BG11+BI11+BK11+BM11+BO11+BQ11+BS11+BU11+BW11+BY11+CA11+CE276 -> 386434 | F11: =H11+J11+L11+CD276+N11+P11+R11+T11+V11+X11+Z11+AB11+AD11+AF11+AH11+AJ11+AL11+AN11+AP11+AR11+AT11+AV11+AX11+AZ11+BB11+BD11+BF11+BH11+BJ11+BL11+BN11+BP11+BR11+BT11+BV11+BX11+BZ11+CB11+CF276 -> 386434 | AK11: 386434 | AR11: 386434
A12: 7 | B12: 46023 | C12: Receving | D12: =F12-E12 -> 0 | E12: =G12+I12+CC277+K12+M12+O12+Q12+S12+U12+W12+Y12+AA12+AC12+AE12+AG12+AI12+AK12+AM12+AO12+AQ12+AS12+AU12+AW12+AY12+BA12+BC12+BE12+BG12+BI12+BK12+BM12+BO12+BQ12+BS12+BU12+BW12+BY12+CA12+CE277 -> 119260 | F12: =H12+J12+L12+CD277+N12+P12+R12+T12+V12+X12+Z12+AB12+AD12+AF12+AH12+AJ12+AL12+AN12+AP12+AR12+AT12+AV12+AX12+AZ12+BB12+BD12+BF12+BH12+BJ12+BL12+BN12+BP12+BR12+BT12+BV12+BX12+BZ12+CB12+CF277 -> 119260 | H12: 34225 | R12: 36240 | T12: 2699 | AQ12: 119260 | BT12: 17598 | BV12: 28498
A13: 8 | B13: 46023 | C13: Refund | D13: =F13-E13 -> 0 | E13: =G13+I13+CC278+K13+M13+O13+Q13+S13+U13+W13+Y13+AA13+AC13+AE13+AG13+AI13+AK13+AM13+AO13+AQ13+AS13+AU13+AW13+AY13+BA13+BC13+BE13+BG13+BI13+BK13+BM13+BO13+BQ13+BS13+BU13+BW13+BY13+CA13+CE278 -> 0 | F13: =H13+J13+L13+CD278+N13+P13+R13+T13+V13+X13+Z13+AB13+AD13+AF13+AH13+AJ13+AL13+AN13+AP13+AR13+AT13+AV13+AX13+AZ13+BB13+BD13+BF13+BH13+BJ13+BL13+BN13+BP13+BR13+BT13+BV13+BX13+BZ13+CB13+CF278 -> 0
A14: 9 | B14: 46023 | C14: inventory | D14: =F14-E14 -> 0 | E14: =G14+I14+CC279+K14+M14+O14+Q14+S14+U14+W14+Y14+AA14+AC14+AE14+AG14+AI14+AK14+AM14+AO14+AQ14+AS14+AU14+AW14+AY14+BA14+BC14+BE14+BG14+BI14+BK14+BM14+BO14+BQ14+BS14+BU14+BW14+BY14+CA14+CE279 -> 128400 | F14: =H14+J14+L14+CD279+N14+P14+R14+T14+V14+X14+Z14+AB14+AD14+AF14+AH14+AJ14+AL14+AN14+AP14+AR14+AT14+AV14+AX14+AZ14+BB14+BD14+BF14+BH14+BJ14+BL14+BN14+BP14+BR14+BT14+BV14+BX14+BZ14+CB14+CF279 -> 128400 | N14: 128400 | AU14: 128400
A15: 10 | B15: 46023 | C15: Saleries | D15: =F15-E15 -> 0 | E15: =G15+I15+CC280+K15+M15+O15+Q15+S15+U15+W15+Y15+AA15+AC15+AE15+AG15+AI15+AK15+AM15+AO15+AQ15+AS15+AU15+AW15+AY15+BA15+BC15+BE15+BG15+BI15+BK15+BM15+BO15+BQ15+BS15+BU15+BW15+BY15+CA15+CE280 -> 271260 | F15: =H15+J15+L15+CD280+N15+P15+R15+T15+V15+X15+Z15+AB15+AD15+AF15+AH15+AJ15+AL15+AN15+AP15+AR15+AT15+AV15+AX15+AZ15+BB15+BD15+BF15+BH15+BJ15+BL15+BN15+BP15+BR15+BT15+BV15+BX15+BZ15+CB15+CF280 -> 271260 | G15: 271260 | AP15: 271260
A16: 11 | B16: 46023 | C16: General expenses | D16: =F16-E16 -> 0 | E16: =G16+I16+CC277+K16+M16+O16+Q16+S16+U16+W16+Y16+AA16+AC16+AE16+AG16+AI16+AK16+AM16+AO16+AQ16+AS16+AU16+AW16+AY16+BA16+BC16+BE16+BG16+BI16+BK16+BM16+BO16+BQ16+BS16+BU16+BW16+BY16+CA16+CE277 -> 24525 | F16: =H16+J16+L16+CD277+N16+P16+R16+T16+V16+X16+Z16+AB16+AD16+AF16+AH16+AJ16+AL16+AN16+AP16+AR16+AT16+AV16+AX16+AZ16+BB16+BD16+BF16+BH16+BJ16+BL16+BN16+BP16+BR16+BT16+BV16+BX16+BZ16+CB16+CF277 -> 24525 | G16: 24525 | AP16: 24525
A17: 12 | B17: 46023 | C17: رد سلف | D17: =F17-E17 -> 0 | E17: =G17+I17+CC278+K17+M17+O17+Q17+S17+U17+W17+Y17+AA17+AC17+AE17+AG17+AI17+AK17+AM17+AO17+AQ17+AS17+AU17+AW17+AY17+BA17+BC17+BE17+BG17+BI17+BK17+BM17+BO17+BQ17+BS17+BU17+BW17+BY17+CA17+CE278 -> 7500 | F17: =H17+J17+L17+CD278+N17+P17+R17+T17+V17+X17+Z17+AB17+AD17+AF17+AH17+AJ17+AL17+AN17+AP17+AR17+AT17+AV17+AX17+AZ17+BB17+BD17+BF17+BH17+BJ17+BL17+BN17+BP17+BR17+BT17+BV17+BX17+BZ17+CB17+CF278 -> 7500 | H17: 7500 | BQ17: 7500
A18: 1 | B18: 46024 | C18: Sales | D18: =F18-E18 -> 0 | E18: =G18+I18+CC279+K18+M18+O18+Q18+S18+U18+W18+Y18+AA18+AC18+AE18+AG18+AI18+AK18+AM18+AO18+AQ18+AS18+AU18+AW18+AY18+BA18+BC18+BE18+BG18+BI18+BK18+BM18+BO18+BQ18+BS18+BU18+BW18+BY18+CA18+CE279 -> 519449 | F18: =H18+J18+L18+CD279+N18+P18+R18+T18+V18+X18+Z18+AB18+AD18+AF18+AH18+AJ18+AL18+AN18+AP18+AR18+AT18+AV18+AX18+AZ18+BB18+BD18+BF18+BH18+BJ18+BL18+BN18+BP18+BR18+BT18+BV18+BX18+BZ18+CB18+CF279 -> 519449 | O18: 473227 | AK18: 46222 | AL18: 473227 | AX18: 46222
A19: 2 | B19: 46024 | C19: Returns | D19: =F19-E19 -> 0 | E19: =G19+I19+CC280+K19+M19+O19+Q19+S19+U19+W19+Y19+AA19+AC19+AE19+AG19+AI19+AK19+AM19+AO19+AQ19+AS19+AU19+AW19+AY19+BA19+BC19+BE19+BG19+BI19+BK19+BM19+BO19+BQ19+BS19+BU19+BW19+BY19+CA19+CE280 -> 0 | F19: =H19+J19+L19+CD280+N19+P19+R19+T19+V19+X19+Z19+AB19+AD19+AF19+AH19+AJ19+AL19+AN19+AP19+AR19+AT19+AV19+AX19+AZ19+BB19+BD19+BF19+BH19+BJ19+BL19+BN19+BP19+BR19+BT19+BV19+BX19+BZ19+CB19+CF280 -> 0
A20: 3 | B20: 46024 | C20: Returns Cost | D20: =F20-E20 -> 0 | E20: =G20+I20+CC281+K20+M20+O20+Q20+S20+U20+W20+Y20+AA20+AC20+AE20+AG20+AI20+AK20+AM20+AO20+AQ20+AS20+AU20+AW20+AY20+BA20+BC20+BE20+BG20+BI20+BK20+BM20+BO20+BQ20+BS20+BU20+BW20+BY20+CA20+CE281 -> 0 | F20: =H20+J20+L20+CD281+N20+P20+R20+T20+V20+X20+Z20+AB20+AD20+AF20+AH20+AJ20+AL20+AN20+AP20+AR20+AT20+AV20+AX20+AZ20+BB20+BD20+BF20+BH20+BJ20+BL20+BN20+BP20+BR20+BT20+BV20+BX20+BZ20+CB20+CF281 -> 0
A21: 4 | B21: 46024 | C21: Cost | D21: =F21-E21 -> 0 | E21: =G21+I21+CC283+K21+M21+O21+Q21+S21+U21+W21+Y21+AA21+AC21+AE21+AG21+AI21+AK21+AM21+AO21+AQ21+AS21+AU21+AW21+AY21+BA21+BC21+BE21+BG21+BI21+BK21+BM21+BO21+BQ21+BS21+BU21+BW21+BY21+CA21+CE283 -> 200320 | F21: =H21+J21+L21+CD283+N21+P21+R21+T21+V21+X21+Z21+AB21+AD21+AF21+AH21+AJ21+AL21+AN21+AP21+AR21+AT21+AV21+AX21+AZ21+BB21+BD21+BF21+BH21+BJ21+BL21+BN21+BP21+BR21+BT21+BV21+BX21+BZ21+CB21+CF283 -> 200320 | M21: 200320 | AT21: 200320
A22: 5 | B22: 46024 | C22: Shipping | D22: =F22-E22 -> 0 | E22: =G22+I22+CC284+K22+M22+O22+Q22+S22+U22+W22+Y22+AA22+AC22+AE22+AG22+AI22+AK22+AM22+AO22+AQ22+AS22+AU22+AW22+AY22+BA22+BC22+BE22+BG22+BI22+BK22+BM22+BO22+BQ22+BS22+BU22+BW22+BY22+CA22+CE284 -> 0 | F22: =H22+J22+L22+CD284+N22+P22+R22+T22+V22+X22+Z22+AB22+AD22+AF22+AH22+AJ22+AL22+AN22+AP22+AR22+AT22+AV22+AX22+AZ22+BB22+BD22+BF22+BH22+BJ22+BL22+BN22+BP22+BR22+BT22+BV22+BX22+BZ22+CB22+CF284 -> 0
A23: 6 | B23: 46024 | C23: Pickup | D23: =F23-E23 -> 0 | E23: =G23+I23+CC285+K23+M23+O23+Q23+S23+U23+W23+Y23+AA23+AC23+AE23+AG23+AI23+AK23+AM23+AO23+AQ23+AS23+AU23+AW23+AY23+BA23+BC23+BE23+BG23+BI23+BK23+BM23+BO23+BQ23+BS23+BU23+BW23+BY23+CA23+CE285 -> 0 | F23: =H23+J23+L23+CD285+N23+P23+R23+T23+V23+X23+Z23+AB23+AD23+AF23+AH23+AJ23+AL23+AN23+AP23+AR23+AT23+AV23+AX23+AZ23+BB23+BD23+BF23+BH23+BJ23+BL23+BN23+BP23+BR23+BT23+BV23+BX23+BZ23+CB23+CF285 -> 0
A24: 7 | B24: 46024 | C24: Receving | D24: =F24-E24 -> 0 | E24: =G24+I24+CC285+K24+M24+O24+Q24+S24+U24+W24+Y24+AA24+AC24+AE24+AG24+AI24+AK24+AM24+AO24+AQ24+AS24+AU24+AW24+AY24+BA24+BC24+BE24+BG24+BI24+BK24+BM24+BO24+BQ24+BS24+BU24+BW24+BY24+CA24+CE285 -> 49795 | F24: =H24+J24+L24+CD285+N24+P24+R24+T24+V24+X24+Z24+AB24+AD24+AF24+AH24+AJ24+AL24+AN24+AP24+AR24+AT24+AV24+AX24+AZ24+BB24+BD24+BF24+BH24+BJ24+BL24+BN24+BP24+BR24+BT24+BV24+BX24+BZ24+CB24+CF285 -> 49795 | T24: 25248 | V24: 3999 | AQ24: 49795 | BT24: 20548
A25: 8 | B25: 46024 | C25: Refund | D25: =F25-E25 -> 0 | E25: =G25+I25+CC284+K25+M25+O25+Q25+S25+U25+W25+Y25+AA25+AC25+AE25+AG25+AI25+AK25+AM25+AO25+AQ25+AS25+AU25+AW25+AY25+BA25+BC25+BE25+BG25+BI25+BK25+BM25+BO25+BQ25+BS25+BU25+BW25+BY25+CA25+CE284 -> 0 | F25: =H25+J25+L25+CD284+N25+P25+R25+T25+V25+X25+Z25+AB25+AD25+AF25+AH25+AJ25+AL25+AN25+AP25+AR25+AT25+AV25+AX25+AZ25+BB25+BD25+BF25+BH25+BJ25+BL25+BN25+BP25+BR25+BT25+BV25+BX25+BZ25+CB25+CF284 -> 0
A26: 9 | B26: 46024 | C26: inventory | D26: =F26-E26 -> 0 | E26: =G26+I26+CC285+K26+M26+O26+Q26+S26+U26+W26+Y26+AA26+AC26+AE26+AG26+AI26+AK26+AM26+AO26+AQ26+AS26+AU26+AW26+AY26+BA26+BC26+BE26+BG26+BI26+BK26+BM26+BO26+BQ26+BS26+BU26+BW26+BY26+CA26+CE285 -> 0 | F26: =H26+J26+L26+CD285+N26+P26+R26+T26+V26+X26+Z26+AB26+AD26+AF26+AH26+AJ26+AL26+AN26+AP26+AR26+AT26+AV26+AX26+AZ26+BB26+BD26+BF26+BH26+BJ26+BL26+BN26+BP26+BR26+BT26+BV26+BX26+BZ26+CB26+CF285 -> 0
A27: 1 | B27: 46025 | C27: Sales | D27: =F27-E27 -> 0 | E27: =G27+I27+CC286+K27+M27+O27+Q27+S27+U27+W27+Y27+AA27+AC27+AE27+AG27+AI27+AK27+AM27+AO27+AQ27+AS27+AU27+AW27+AY27+BA27+BC27+BE27+BG27+BI27+BK27+BM27+BO27+BQ27+BS27+BU27+BW27+BY27+CA27+CE286 -> 583224 | F27: =H27+J27+L27+CD286+N27+P27+R27+T27+V27+X27+Z27+AB27+AD27+AF27+AH27+AJ27+AL27+AN27+AP27+AR27+AT27+AV27+AX27+AZ27+BB27+BD27+BF27+BH27+BJ27+BL27+BN27+BP27+BR27+BT27+BV27+BX27+BZ27+CB27+CF286 -> 583224 | O27: 536134 | AK27: 47090 | AL27: 536134 | AX27: 47090
A28: 2 | B28: 46025 | C28: Returns | D28: =F28-E28 -> 0 | E28: =G28+I28+CC287+K28+M28+O28+Q28+S28+U28+W28+Y28+AA28+AC28+AE28+AG28+AI28+AK28+AM28+AO28+AQ28+AS28+AU28+AW28+AY28+BA28+BC28+BE28+BG28+BI28+BK28+BM28+BO28+BQ28+BS28+BU28+BW28+BY28+CA28+CE287 -> 128236 | F28: =H28+J28+L28+CD287+N28+P28+R28+T28+V28+X28+Z28+AB28+AD28+AF28+AH28+AJ28+AL28+AN28+AP28+AR28+AT28+AV28+AX28+AZ28+BB28+BD28+BF28+BH28+BJ28+BL28+BN28+BP28+BR28+BT28+BV28+BX28+BZ28+CB28+CF287 -> 128236 | P28: 128236 | AQ28: 128236
A29: 3 | B29: 46025 | C29: Returns Cost | D29: =F29-E29 -> 0 | E29: =G29+I29+CC291+K29+M29+O29+Q29+S29+U29+W29+Y29+AA29+AC29+AE29+AG29+AI29+AK29+AM29+AO29+AQ29+AS29+AU29+AW29+AY29+BA29+BC29+BE29+BG29+BI29+BK29+BM29+BO29+BQ29+BS29+BU29+BW29+BY29+CA29+CE291 -> 57400 | F29: =H29+J29+L29+CD291+N29+P29+R29+T29+V29+X29+Z29+AB29+AD29+AF29+AH29+AJ29+AL29+AN29+AP29+AR29+AT29+AV29+AX29+AZ29+BB29+BD29+BF29+BH29+BJ29+BL29+BN29+BP29+BR29+BT29+BV29+BX29+BZ29+CB29+CF291 -> 57400 | N29: 57400 | AS29: 57400
A30: 4 | B30: 46025 | C30: Cost | D30: =F30-E30 -> 0 | E30: =G30+I30+CC292+K30+M30+O30+Q30+S30+U30+W30+Y30+AA30+AC30+AE30+AG30+AI30+AK30+AM30+AO30+AQ30+AS30+AU30+AW30+AY30+BA30+BC30+BE30+BG30+BI30+BK30+BM30+BO30+BQ30+BS30+BU30+BW30+BY30+CA30+CE292 -> 221700 | F30: =H30+J30+L30+CD292+N30+P30+R30+T30+V30+X30+Z30+AB30+AD30+AF30+AH30+AJ30+AL30+AN30+AP30+AR30+AT30+AV30+AX30+AZ30+BB30+BD30+BF30+BH30+BJ30+BL30+BN30+BP30+BR30+BT30+BV30+BX30+BZ30+CB30+CF292 -> 221700 | M30: 221700 | AT30: 221700
A31: 5 | B31: 46025 | C31: Shipping | D31: =F31-E31 -> 0 | E31: =G31+I31+CC293+K31+M31+O31+Q31+S31+U31+W31+Y31+AA31+AC31+AE31+AG31+AI31+AK31+AM31+AO31+AQ31+AS31+AU31+AW31+AY31+BA31+BC31+BE31+BG31+BI31+BK31+BM31+BO31+BQ31+BS31+BU31+BW31+BY31+CA31+CE293 -> 2115 | F31: =H31+J31+L31+CD293+N31+P31+R31+T31+V31+X31+Z31+AB31+AD31+AF31+AH31+AJ31+AL31+AN31+AP31+AR31+AT31+AV31+AX31+AZ31+BB31+BD31+BF31+BH31+BJ31+BL31+BN31+BP31+BR31+BT31+BV31+BX31+BZ31+CB31+CF293 -> 2115 | G31: 2115 | AN31: 2115
A32: 6 | B32: 46025 | C32: Pickup | D32: =F32-E32 -> 0 | E32: =G32+I32+CC294+K32+M32+O32+Q32+S32+U32+W32+Y32+AA32+AC32+AE32+AG32+AI32+AK32+AM32+AO32+AQ32+AS32+AU32+AW32+AY32+BA32+BC32+BE32+BG32+BI32+BK32+BM32+BO32+BQ32+BS32+BU32+BW32+BY32+CA32+CE294 -> 670751 | F32: =H32+J32+L32+CD294+N32+P32+R32+T32+V32+X32+Z32+AB32+AD32+AF32+AH32+AJ32+AL32+AN32+AP32+AR32+AT32+AV32+AX32+AZ32+BB32+BD32+BF32+BH32+BJ32+BL32+BN32+BP32+BR32+BT32+BV32+BX32+BZ32+CB32+CF294 -> 670751 | AK32: 670751 | AR32: 670751
A33: 7 | B33: 46025 | C33: Receving | D33: =F33-E33 -> 0 | E33: =G33+I33+CC294+K33+M33+O33+Q33+S33+U33+W33+Y33+AA33+AC33+AE33+AG33+AI33+AK33+AM33+AO33+AQ33+AS33+AU33+AW33+AY33+BA33+BC33+BE33+BG33+BI33+BK33+BM33+BO33+BQ33+BS33+BU33+BW33+BY33+CA33+CE294 -> 201617 | F33: =H33+J33+L33+CD294+N33+P33+R33+T33+V33+X33+Z33+AB33+AD33+AF33+AH33+AJ33+AL33+AN33+AP33+AR33+AT33+AV33+AX33+AZ33+BB33+BD33+BF33+BH33+BJ33+BL33+BN33+BP33+BR33+BT33+BV33+BX33+BZ33+CB33+CF294 -> 201617 | H33: 69474 | J33: 16600 | R33: 32897 | V33: 21499 | AQ33: 201617 | BV33: 61147
A34: 8 | B34: 46025 | C34: Refund | D34: =F34-E34 -> 0 | E34: =G34+I34+CC295+K34+M34+O34+Q34+S34+U34+W34+Y34+AA34+AC34+AE34+AG34+AI34+AK34+AM34+AO34+AQ34+AS34+AU34+AW34+AY34+BA34+BC34+BE34+BG34+BI34+BK34+BM34+BO34+BQ34+BS34+BU34+BW34+BY34+CA34+CE295 -> 15615 | F34: =H34+J34+L34+CD295+N34+P34+R34+T34+V34+X34+Z34+AB34+AD34+AF34+AH34+AJ34+AL34+AN34+AP34+AR34+AT34+AV34+AX34+AZ34+BB34+BD34+BF34+BH34+BJ34+BL34+BN34+BP34+BR34+BT34+BV34+BX34+BZ34+CB34+CF295 -> 15615 | S34: 7400 | U34: 8215 | AZ34: 15615
A35: 9 | B35: 46025 | C35: inventory | D35: =F35-E35 -> 0 | E35: =G35+I35+CC296+K35+M35+O35+Q35+S35+U35+W35+Y35+AA35+AC35+AE35+AG35+AI35+AK35+AM35+AO35+AQ35+AS35+AU35+AW35+AY35+BA35+BC35+BE35+BG35+BI35+BK35+BM35+BO35+BQ35+BS35+BU35+BW35+BY35+CA35+CE296 -> 0 | F35: =H35+J35+L35+CD296+N35+P35+R35+T35+V35+X35+Z35+AB35+AD35+AF35+AH35+AJ35+AL35+AN35+AP35+AR35+AT35+AV35+AX35+AZ35+BB35+BD35+BF35+BH35+BJ35+BL35+BN35+BP35+BR35+BT35+BV35+BX35+BZ35+CB35+CF296 -> 0
A36: 10 | B36: 46025 | C36: General expenses | D36: =F36-E36 -> 0 | E36: =G36+I36+CC297+K36+M36+O36+Q36+S36+U36+W36+Y36+AA36+AC36+AE36+AG36+AI36+AK36+AM36+AO36+AQ36+AS36+AU36+AW36+AY36+BA36+BC36+BE36+BG36+BI36+BK36+BM36+BO36+BQ36+BS36+BU36+BW36+BY36+CA36+CE297 -> 18725 | F36: =H36+J36+L36+CD297+N36+P36+R36+T36+V36+X36+Z36+AB36+AD36+AF36+AH36+AJ36+AL36+AN36+AP36+AR36+AT36+AV36+AX36+AZ36+BB36+BD36+BF36+BH36+BJ36+BL36+BN36+BP36+BR36+BT36+BV36+BX36+BZ36+CB36+CF297 -> 18725 | G36: 18725 | AP36: 18725
A37: 1 | B37: 46026 | C37: Sales | D37: =F37-E37 -> 0 | E37: =G37+I37+CC293+K37+M37+O37+Q37+S37+U37+W37+Y37+AA37+AC37+AE37+AG37+AI37+AK37+AM37+AO37+AQ37+AS37+AU37+AW37+AY37+BA37+BC37+BE37+BG37+BI37+BK37+BM37+BO37+BQ37+BS37+BU37+BW37+BY37+CA37+CE293 -> 851115 | F37: =H37+J37+L37+CD293+N37+P37+R37+T37+V37+X37+Z37+AB37+AD37+AF37+AH37+AJ37+AL37+AN37+AP37+AR37+AT37+AV37+AX37+AZ37+BB37+BD37+BF37+BH37+BJ37+BL37+BN37+BP37+BR37+BT37+BV37+BX37+BZ37+CB37+CF293 -> 851115 | O37: 782616 | AK37: 68499 | AL37: 782616 | AX37: 68499
A38: 2 | B38: 46026 | C38: Returns | D38: =F38-E38 -> 0 | E38: =G38+I38+CC284+K38+M38+O38+Q38+S38+U38+W38+Y38+AA38+AC38+AE38+AG38+AI38+AK38+AM38+AO38+AQ38+AS38+AU38+AW38+AY38+BA38+BC38+BE38+BG38+BI38+BK38+BM38+BO38+BQ38+BS38+BU38+BW38+BY38+CA38+CE284 -> 714375 | F38: =H38+J38+L38+CD284+N38+P38+R38+T38+V38+X38+Z38+AB38+AD38+AF38+AH38+AJ38+AL38+AN38+AP38+AR38+AT38+AV38+AX38+AZ38+BB38+BD38+BF38+BH38+BJ38+BL38+BN38+BP38+BR38+BT38+BV38+BX38+BZ38+CB38+CF284 -> 714375 | P38: 714375 | AQ38: 714375
A39: 3 | B39: 46026 | C39: Returns Cost | D39: =F39-E39 -> 0 | E39: =G39+I39+CC285+K39+M39+O39+Q39+S39+U39+W39+Y39+AA39+AC39+AE39+AG39+AI39+AK39+AM39+AO39+AQ39+AS39+AU39+AW39+AY39+BA39+BC39+BE39+BG39+BI39+BK39+BM39+BO39+BQ39+BS39+BU39+BW39+BY39+CA39+CE285 -> 342720 | F39: =H39+J39+L39+CD285+N39+P39+R39+T39+V39+X39+Z39+AB39+AD39+AF39+AH39+AJ39+AL39+AN39+AP39+AR39+AT39+AV39+AX39+AZ39+BB39+BD39+BF39+BH39+BJ39+BL39+BN39+BP39+BR39+BT39+BV39+BX39+BZ39+CB39+CF285 -> 342720 | N39: 342720 | AS39: 342720
A40: 4 | B40: 46026 | C40: Cost | D40: =F40-E40 -> 0 | E40: =G40+I40+CC286+K40+M40+O40+Q40+S40+U40+W40+Y40+AA40+AC40+AE40+AG40+AI40+AK40+AM40+AO40+AQ40+AS40+AU40+AW40+AY40+BA40+BC40+BE40+BG40+BI40+BK40+BM40+BO40+BQ40+BS40+BU40+BW40+BY40+CA40+CE286 -> 358330 | F40: =H40+J40+L40+CD286+N40+P40+R40+T40+V40+X40+Z40+AB40+AD40+AF40+AH40+AJ40+AL40+AN40+AP40+AR40+AT40+AV40+AX40+AZ40+BB40+BD40+BF40+BH40+BJ40+BL40+BN40+BP40+BR40+BT40+BV40+BX40+BZ40+CB40+CF286 -> 358330 | M40: 358330 | AT40: 358330
A41: 5 | B41: 46026 | C41: Shipping | D41: =F41-E41 -> 0 | E41: =G41+I41+CC287+K41+M41+O41+Q41+S41+U41+W41+Y41+AA41+AC41+AE41+AG41+AI41+AK41+AM41+AO41+AQ41+AS41+AU41+AW41+AY41+BA41+BC41+BE41+BG41+BI41+BK41+BM41+BO41+BQ41+BS41+BU41+BW41+BY41+CA41+CE287 -> 3405 | F41: =H41+J41+L41+CD287+N41+P41+R41+T41+V41+X41+Z41+AB41+AD41+AF41+AH41+AJ41+AL41+AN41+AP41+AR41+AT41+AV41+AX41+AZ41+BB41+BD41+BF41+BH41+BJ41+BL41+BN41+BP41+BR41+BT41+BV41+BX41+BZ41+CB41+CF287 -> 3405 | G41: 3405 | AN41: 3405
A42: 6 | B42: 46026 | C42: Pickup | D42: =F42-E42 -> 0 | E42: =G42+I42+CC291+K42+M42+O42+Q42+S42+U42+W42+Y42+AA42+AC42+AE42+AG42+AI42+AK42+AM42+AO42+AQ42+AS42+AU42+AW42+AY42+BA42+BC42+BE42+BG42+BI42+BK42+BM42+BO42+BQ42+BS42+BU42+BW42+BY42+CA42+CE291 -> 640159 | F42: =H42+J42+L42+CD291+N42+P42+R42+T42+V42+X42+Z42+AB42+AD42+AF42+AH42+AJ42+AL42+AN42+AP42+AR42+AT42+AV42+AX42+AZ42+BB42+BD42+BF42+BH42+BJ42+BL42+BN42+BP42+BR42+BT42+BV42+BX42+BZ42+CB42+CF291 -> 640159 | AK42: 640159 | AR42: 640159
A43: 7 | B43: 46026 | C43: Receving | D43: =F43-E43 -> 0 | E43: =G43+I43+CC292+K43+M43+O43+Q43+S43+U43+W43+Y43+AA43+AC43+AE43+AG43+AI43+AK43+AM43+AO43+AQ43+AS43+AU43+AW43+AY43+BA43+BC43+BE43+BG43+BI43+BK43+BM43+BO43+BQ43+BS43+BU43+BW43+BY43+CA43+CE292 -> 280623 | F43: =H43+J43+L43+CD292+N43+P43+R43+T43+V43+X43+Z43+AB43+AD43+AF43+AH43+AJ43+AL43+AN43+AP43+AR43+AT43+AV43+AX43+AZ43+BB43+BD43+BF43+BH43+BJ43+BL43+BN43+BP43+BR43+BT43+BV43+BX43+BZ43+CB43+CF292 -> 280623 | H43: 48045 | J43: 12598 | R43: 33750 | T43: 53659 | V43: 9550 | X43: 5500 | AQ43: 280623 | BT43: 31898 | BV43: 85623
A44: 8 | B44: 46026 | C44: Refund | D44: =F44-E44 -> 0 | E44: =G44+I44+CC292+K44+M44+O44+Q44+S44+U44+W44+Y44+AA44+AC44+AE44+AG44+AI44+AK44+AM44+AO44+AQ44+AS44+AU44+AW44+AY44+BA44+BC44+BE44+BG44+BI44+BK44+BM44+BO44+BQ44+BS44+BU44+BW44+BY44+CA44+CE292 -> 0 | F44: =H44+J44+L44+CD292+N44+P44+R44+T44+V44+X44+Z44+AB44+AD44+AF44+AH44+AJ44+AL44+AN44+AP44+AR44+AT44+AV44+AX44+AZ44+BB44+BD44+BF44+BH44+BJ44+BL44+BN44+BP44+BR44+BT44+BV44+BX44+BZ44+CB44+CF292 -> 0
A45: 9 | B45: 46026 | C45: inventory | D45: =F45-E45 -> 0 | E45: =G45+I45+CC293+K45+M45+O45+Q45+S45+U45+W45+Y45+AA45+AC45+AE45+AG45+AI45+AK45+AM45+AO45+AQ45+AS45+AU45+AW45+AY45+BA45+BC45+BE45+BG45+BI45+BK45+BM45+BO45+BQ45+BS45+BU45+BW45+BY45+CA45+CE293 -> 0 | F45: =H45+J45+L45+CD293+N45+P45+R45+T45+V45+X45+Z45+AB45+AD45+AF45+AH45+AJ45+AL45+AN45+AP45+AR45+AT45+AV45+AX45+AZ45+BB45+BD45+BF45+BH45+BJ45+BL45+BN45+BP45+BR45+BT45+BV45+BX45+BZ45+CB45+CF293 -> 0
A46: 10 | B46: 46026 | C46: General expenses | D46: =F46-E46 -> 0 | E46: =G46+I46+CC294+K46+M46+O46+Q46+S46+U46+W46+Y46+AA46+AC46+AE46+AG46+AI46+AK46+AM46+AO46+AQ46+AS46+AU46+AW46+AY46+BA46+BC46+BE46+BG46+BI46+BK46+BM46+BO46+BQ46+BS46+BU46+BW46+BY46+CA46+CE294 -> 55000 | F46: =H46+J46+L46+CD294+N46+P46+R46+T46+V46+X46+Z46+AB46+AD46+AF46+AH46+AJ46+AL46+AN46+AP46+AR46+AT46+AV46+AX46+AZ46+BB46+BD46+BF46+BH46+BJ46+BL46+BN46+BP46+BR46+BT46+BV46+BX46+BZ46+CB46+CF294 -> 55000 | G46: 55000 | AP46: 55000
A47: 1 | B47: 46027 | C47: Sales | D47: =F47-E47 -> 0 | E47: =G47+I47+CC295+K47+M47+O47+Q47+S47+U47+W47+Y47+AA47+AC47+AE47+AG47+AI47+AK47+AM47+AO47+AQ47+AS47+AU47+AW47+AY47+BA47+BC47+BE47+BG47+BI47+BK47+BM47+BO47+BQ47+BS47+BU47+BW47+BY47+CA47+CE295 -> 565285 | F47: =H47+J47+L47+CD295+N47+P47+R47+T47+V47+X47+Z47+AB47+AD47+AF47+AH47+AJ47+AL47+AN47+AP47+AR47+AT47+AV47+AX47+AZ47+BB47+BD47+BF47+BH47+BJ47+BL47+BN47+BP47+BR47+BT47+BV47+BX47+BZ47+CB47+CF295 -> 565285 | O47: 512076 | AK47: 53209 | AL47: 512076 | AX47: 53209
A48: 2 | B48: 46027 | C48: Returns | D48: =F48-E48 -> 0 | E48: =G48+I48+CC296+K48+M48+O48+Q48+S48+U48+W48+Y48+AA48+AC48+AE48+AG48+AI48+AK48+AM48+AO48+AQ48+AS48+AU48+AW48+AY48+BA48+BC48+BE48+BG48+BI48+BK48+BM48+BO48+BQ48+BS48+BU48+BW48+BY48+CA48+CE296 -> 198836 | F48: =H48+J48+L48+CD296+N48+P48+R48+T48+V48+X48+Z48+AB48+AD48+AF48+AH48+AJ48+AL48+AN48+AP48+AR48+AT48+AV48+AX48+AZ48+BB48+BD48+BF48+BH48+BJ48+BL48+BN48+BP48+BR48+BT48+BV48+BX48+BZ48+CB48+CF296 -> 198836 | P48: 198836 | AQ48: 198836
A49: 3 | B49: 46027 | C49: Returns Cost | D49: =F49-E49 -> 0 | E49: =G49+I49+CC302+K49+M49+O49+Q49+S49+U49+W49+Y49+AA49+AC49+AE49+AG49+AI49+AK49+AM49+AO49+AQ49+AS49+AU49+AW49+AY49+BA49+BC49+BE49+BG49+BI49+BK49+BM49+BO49+BQ49+BS49+BU49+BW49+BY49+CA49+CE302 -> 132300 | F49: =H49+J49+L49+CD302+N49+P49+R49+T49+V49+X49+Z49+AB49+AD49+AF49+AH49+AJ49+AL49+AN49+AP49+AR49+AT49+AV49+AX49+AZ49+BB49+BD49+BF49+BH49+BJ49+BL49+BN49+BP49+BR49+BT49+BV49+BX49+BZ49+CB49+CF302 -> 132300 | N49: 132300 | AS49: 132300
A50: 4 | B50: 46027 | C50: Cost | D50: =F50-E50 -> 0 | E50: =G50+I50+CC303+K50+M50+O50+Q50+S50+U50+W50+Y50+AA50+AC50+AE50+AG50+AI50+AK50+AM50+AO50+AQ50+AS50+AU50+AW50+AY50+BA50+BC50+BE50+BG50+BI50+BK50+BM50+BO50+BQ50+BS50+BU50+BW50+BY50+CA50+CE303 -> 294920 | F50: =H50+J50+L50+CD303+N50+P50+R50+T50+V50+X50+Z50+AB50+AD50+AF50+AH50+AJ50+AL50+AN50+AP50+AR50+AT50+AV50+AX50+AZ50+BB50+BD50+BF50+BH50+BJ50+BL50+BN50+BP50+BR50+BT50+BV50+BX50+BZ50+CB50+CF303 -> 294920 | M50: 294920 | AT50: 294920
A51: 5 | B51: 46027 | C51: Shipping | D51: =F51-E51 -> 0 | E51: =G51+I51+CC304+K51+M51+O51+Q51+S51+U51+W51+Y51+AA51+AC51+AE51+AG51+AI51+AK51+AM51+AO51+AQ51+AS51+AU51+AW51+AY51+BA51+BC51+BE51+BG51+BI51+BK51+BM51+BO51+BQ51+BS51+BU51+BW51+BY51+CA51+CE304 -> 11985 | F51: =H51+J51+L51+CD304+N51+P51+R51+T51+V51+X51+Z51+AB51+AD51+AF51+AH51+AJ51+AL51+AN51+AP51+AR51+AT51+AV51+AX51+AZ51+BB51+BD51+BF51+BH51+BJ51+BL51+BN51+BP51+BR51+BT51+BV51+BX51+BZ51+CB51+CF304 -> 11985 | G51: 11985 | AN51: 11985
A52: 6 | B52: 46027 | C52: Pickup | D52: =F52-E52 -> 0 | E52: =G52+I52+CC305+K52+M52+O52+Q52+S52+U52+W52+Y52+AA52+AC52+AE52+AG52+AI52+AK52+AM52+AO52+AQ52+AS52+AU52+AW52+AY52+BA52+BC52+BE52+BG52+BI52+BK52+BM52+BO52+BQ52+BS52+BU52+BW52+BY52+CA52+CE305 -> 559131 | F52: =H52+J52+L52+CD305+N52+P52+R52+T52+V52+X52+Z52+AB52+AD52+AF52+AH52+AJ52+AL52+AN52+AP52+AR52+AT52+AV52+AX52+AZ52+BB52+BD52+BF52+BH52+BJ52+BL52+BN52+BP52+BR52+BT52+BV52+BX52+BZ52+CB52+CF305 -> 559131 | AK52: 559131 | AR52: 559131
A53: 7 | B53: 46027 | C53: Receving | D53: =F53-E53 -> 0 | E53: =G53+I53+CC292+K53+M53+O53+Q53+S53+U53+W53+Y53+AA53+AC53+AE53+AG53+AI53+AK53+AM53+AO53+AQ53+AS53+AU53+AW53+AY53+BA53+BC53+BE53+BG53+BI53+BK53+BM53+BO53+BQ53+BS53+BU53+BW53+BY53+CA53+CE292 -> 589007 | F53: =H53+J53+L53+CD292+N53+P53+R53+T53+V53+X53+Z53+AB53+AD53+AF53+AH53+AJ53+AL53+AN53+AP53+AR53+AT53+AV53+AX53+AZ53+BB53+BD53+BF53+BH53+BJ53+BL53+BN53+BP53+BR53+BT53+BV53+BX53+BZ53+CB53+CF292 -> 589007 | H53: 315820 | J53: 13299 | L53: 15600 | R53: 86048 | T53: 4799 | V53: 60496 | AQ53: 589007 | BT53: 14299 | BV53: 78646
A54: 8 | B54: 46027 | C54: Refund | D54: =F54-E54 -> 0 | E54: =G54+I54+CC293+K54+M54+O54+Q54+S54+U54+W54+Y54+AA54+AC54+AE54+AG54+AI54+AK54+AM54+AO54+AQ54+AS54+AU54+AW54+AY54+BA54+BC54+BE54+BG54+BI54+BK54+BM54+BO54+BQ54+BS54+BU54+BW54+BY54+CA54+CE293 -> 0 | F54: =H54+J54+L54+CD293+N54+P54+R54+T54+V54+X54+Z54+AB54+AD54+AF54+AH54+AJ54+AL54+AN54+AP54+AR54+AT54+AV54+AX54+AZ54+BB54+BD54+BF54+BH54+BJ54+BL54+BN54+BP54+BR54+BT54+BV54+BX54+BZ54+CB54+CF293 -> 0
A55: 9 | B55: 46027 | C55: inventory | D55: =F55-E55 -> 0 | E55: =G55+I55+CC294+K55+M55+O55+Q55+S55+U55+W55+Y55+AA55+AC55+AE55+AG55+AI55+AK55+AM55+AO55+AQ55+AS55+AU55+AW55+AY55+BA55+BC55+BE55+BG55+BI55+BK55+BM55+BO55+BQ55+BS55+BU55+BW55+BY55+CA55+CE294 -> 0 | F55: =H55+J55+L55+CD294+N55+P55+R55+T55+V55+X55+Z55+AB55+AD55+AF55+AH55+AJ55+AL55+AN55+AP55+AR55+AT55+AV55+AX55+AZ55+BB55+BD55+BF55+BH55+BJ55+BL55+BN55+BP55+BR55+BT55+BV55+BX55+BZ55+CB55+CF294 -> 0
A56: 10 | B56: 46027 | C56: General expenses | D56: =F56-E56 -> 0 | E56: =G56+I56+CC295+K56+M56+O56+Q56+S56+U56+W56+Y56+AA56+AC56+AE56+AG56+AI56+AK56+AM56+AO56+AQ56+AS56+AU56+AW56+AY56+BA56+BC56+BE56+BG56+BI56+BK56+BM56+BO56+BQ56+BS56+BU56+BW56+BY56+CA56+CE295 -> 110 | F56: =H56+J56+L56+CD295+N56+P56+R56+T56+V56+X56+Z56+AB56+AD56+AF56+AH56+AJ56+AL56+AN56+AP56+AR56+AT56+AV56+AX56+AZ56+BB56+BD56+BF56+BH56+BJ56+BL56+BN56+BP56+BR56+BT56+BV56+BX56+BZ56+CB56+CF295 -> 110 | G56: 110 | AP56: 110
A57: 1 | B57: 46028 | C57: Sales | D57: =F57-E57 -> 0 | E57: =G57+I57+CC296+K57+M57+O57+Q57+S57+U57+W57+Y57+AA57+AC57+AE57+AG57+AI57+AK57+AM57+AO57+AQ57+AS57+AU57+AW57+AY57+BA57+BC57+BE57+BG57+BI57+BK57+BM57+BO57+BQ57+BS57+BU57+BW57+BY57+CA57+CE296 -> 558092 | F57: =H57+J57+L57+CD296+N57+P57+R57+T57+V57+X57+Z57+AB57+AD57+AF57+AH57+AJ57+AL57+AN57+AP57+AR57+AT57+AV57+AX57+AZ57+BB57+BD57+BF57+BH57+BJ57+BL57+BN57+BP57+BR57+BT57+BV57+BX57+BZ57+CB57+CF296 -> 558092 | O57: 524713 | AK57: 33379 | AL57: 524713 | AX57: 33379
A58: 2 | B58: 46028 | C58: Returns | D58: =F58-E58 -> 0 | E58: =G58+I58+CC302+K58+M58+O58+Q58+S58+U58+W58+Y58+AA58+AC58+AE58+AG58+AI58+AK58+AM58+AO58+AQ58+AS58+AU58+AW58+AY58+BA58+BC58+BE58+BG58+BI58+BK58+BM58+BO58+BQ58+BS58+BU58+BW58+BY58+CA58+CE302 -> 552014 | F58: =H58+J58+L58+CD302+N58+P58+R58+T58+V58+X58+Z58+AB58+AD58+AF58+AH58+AJ58+AL58+AN58+AP58+AR58+AT58+AV58+AX58+AZ58+BB58+BD58+BF58+BH58+BJ58+BL58+BN58+BP58+BR58+BT58+BV58+BX58+BZ58+CB58+CF302 -> 552014 | P58: 552014 | AQ58: 552014
A59: 3 | B59: 46028 | C59: Returns Cost | D59: =F59-E59 -> 0 | E59: =G59+I59+CC303+K59+M59+O59+Q59+S59+U59+W59+Y59+AA59+AC59+AE59+AG59+AI59+AK59+AM59+AO59+AQ59+AS59+AU59+AW59+AY59+BA59+BC59+BE59+BG59+BI59+BK59+BM59+BO59+BQ59+BS59+BU59+BW59+BY59+CA59+CE303 -> 254750 | F59: =H59+J59+L59+CD303+N59+P59+R59+T59+V59+X59+Z59+AB59+AD59+AF59+AH59+AJ59+AL59+AN59+AP59+AR59+AT59+AV59+AX59+AZ59+BB59+BD59+BF59+BH59+BJ59+BL59+BN59+BP59+BR59+BT59+BV59+BX59+BZ59+CB59+CF303 -> 254750 | N59: 254750 | AS59: 254750
A60: 4 | B60: 46028 | C60: Cost | D60: =F60-E60 -> 0 | E60: =G60+I60+CC304+K60+M60+O60+Q60+S60+U60+W60+Y60+AA60+AC60+AE60+AG60+AI60+AK60+AM60+AO60+AQ60+AS60+AU60+AW60+AY60+BA60+BC60+BE60+BG60+BI60+BK60+BM60+BO60+BQ60+BS60+BU60+BW60+BY60+CA60+CE304 -> 227600 | F60: =H60+J60+L60+CD304+N60+P60+R60+T60+V60+X60+Z60+AB60+AD60+AF60+AH60+AJ60+AL60+AN60+AP60+AR60+AT60+AV60+AX60+AZ60+BB60+BD60+BF60+BH60+BJ60+BL60+BN60+BP60+BR60+BT60+BV60+BX60+BZ60+CB60+CF304 -> 227600 | M60: 227600 | AT60: 227600
A61: 5 | B61: 46028 | C61: Shipping | D61: =F61-E61 -> 0 | E61: =G61+I61+CC305+K61+M61+O61+Q61+S61+U61+W61+Y61+AA61+AC61+AE61+AG61+AI61+AK61+AM61+AO61+AQ61+AS61+AU61+AW61+AY61+BA61+BC61+BE61+BG61+BI61+BK61+BM61+BO61+BQ61+BS61+BU61+BW61+BY61+CA61+CE305 -> 4450 | F61: =H61+J61+L61+CD305+N61+P61+R61+T61+V61+X61+Z61+AB61+AD61+AF61+AH61+AJ61+AL61+AN61+AP61+AR61+AT61+AV61+AX61+AZ61+BB61+BD61+BF61+BH61+BJ61+BL61+BN61+BP61+BR61+BT61+BV61+BX61+BZ61+CB61+CF305 -> 4450 | G61: 4450 | AN61: 4450
A62: 6 | B62: 46028 | C62: Pickup | D62: =F62-E62 -> 0 | E62: =G62+I62+CC277+K62+M62+O62+Q62+S62+U62+W62+Y62+AA62+AC62+AE62+AG62+AI62+AK62+AM62+AO62+AQ62+AS62+AU62+AW62+AY62+BA62+BC62+BE62+BG62+BI62+BK62+BM62+BO62+BQ62+BS62+BU62+BW62+BY62+CA62+CE277 -> 741928 | F62: =H62+J62+L62+CD277+N62+P62+R62+T62+V62+X62+Z62+AB62+AD62+AF62+AH62+AJ62+AL62+AN62+AP62+AR62+AT62+AV62+AX62+AZ62+BB62+BD62+BF62+BH62+BJ62+BL62+BN62+BP62+BR62+BT62+BV62+BX62+BZ62+CB62+CF277 -> 741928 | AK62: 741928 | AR62: 741928
A63: 7 | B63: 46028 | C63: Receving | D63: =F63-E63 -> 0 | E63: =G63+I63+CC268+K63+M63+O63+Q63+S63+U63+W63+Y63+AA63+AC63+AE63+AG63+AI63+AK63+AM63+AO63+AQ63+AS63+AU63+AW63+AY63+BA63+BC63+BE63+BG63+BI63+BK63+BM63+BO63+BQ63+BS63+BU63+BW63+BY63+CA63+CE268 -> 216809 | F63: =H63+J63+L63+CD268+N63+P63+R63+T63+V63+X63+Z63+AB63+AD63+AF63+AH63+AJ63+AL63+AN63+AP63+AR63+AT63+AV63+AX63+AZ63+BB63+BD63+BF63+BH63+BJ63+BL63+BN63+BP63+BR63+BT63+BV63+BX63+BZ63+CB63+CF268 -> 216809 | H63: 59090 | R63: 7750 | T63: 41073 | AQ63: 216809 | BT63: 43446 | BV63: 65450
A64: 8 | B64: 46028 | C64: Refund | D64: =F64-E64 -> 0 | E64: =G64+I64+CC269+K64+M64+O64+Q64+S64+U64+W64+Y64+AA64+AC64+AE64+AG64+AI64+AK64+AM64+AO64+AQ64+AS64+AU64+AW64+AY64+BA64+BC64+BE64+BG64+BI64+BK64+BM64+BO64+BQ64+BS64+BU64+BW64+BY64+CA64+CE269 -> 11700 | F64: =H64+J64+L64+CD269+N64+P64+R64+T64+V64+X64+Z64+AB64+AD64+AF64+AH64+AJ64+AL64+AN64+AP64+AR64+AT64+AV64+AX64+AZ64+BB64+BD64+BF64+BH64+BJ64+BL64+BN64+BP64+BR64+BT64+BV64+BX64+BZ64+CB64+CF269 -> 11700 | Q64: 11700 | AZ64: 11700
A65: 9 | B65: 46028 | C65: inventory | D65: =F65-E65 -> 0 | E65: =G65+I65+CC270+K65+M65+O65+Q65+S65+U65+W65+Y65+AA65+AC65+AE65+AG65+AI65+AK65+AM65+AO65+AQ65+AS65+AU65+AW65+AY65+BA65+BC65+BE65+BG65+BI65+BK65+BM65+BO65+BQ65+BS65+BU65+BW65+BY65+CA65+CE270 -> 0 | F65: =H65+J65+L65+CD270+N65+P65+R65+T65+V65+X65+Z65+AB65+AD65+AF65+AH65+AJ65+AL65+AN65+AP65+AR65+AT65+AV65+AX65+AZ65+BB65+BD65+BF65+BH65+BJ65+BL65+BN65+BP65+BR65+BT65+BV65+BX65+BZ65+CB65+CF270 -> 0
A66: 1 | B66: 46029 | C66: Sales | D66: =F66-E66 -> 0 | E66: =G66+I66+CC271+K66+M66+O66+Q66+S66+U66+W66+Y66+AA66+AC66+AE66+AG66+AI66+AK66+AM66+AO66+AQ66+AS66+AU66+AW66+AY66+BA66+BC66+BE66+BG66+BI66+BK66+BM66+BO66+BQ66+BS66+BU66+BW66+BY66+CA66+CE271 -> 818423 | F66: =H66+J66+L66+CD271+N66+P66+R66+T66+V66+X66+Z66+AB66+AD66+AF66+AH66+AJ66+AL66+AN66+AP66+AR66+AT66+AV66+AX66+AZ66+BB66+BD66+BF66+BH66+BJ66+BL66+BN66+BP66+BR66+BT66+BV66+BX66+BZ66+CB66+CF271 -> 818423 | O66: 759100 | AK66: 59323 | AL66: 759100 | AX66: 59323
A67: 2 | B67: 46029 | C67: Returns | D67: =F67-E67 -> 0 | E67: =G67+I67+CC276+K67+M67+O67+Q67+S67+U67+W67+Y67+AA67+AC67+AE67+AG67+AI67+AK67+AM67+AO67+AQ67+AS67+AU67+AW67+AY67+BA67+BC67+BE67+BG67+BI67+BK67+BM67+BO67+BQ67+BS67+BU67+BW67+BY67+CA67+CE276 -> 311458 | F67: =H67+J67+L67+CD276+N67+P67+R67+T67+V67+X67+Z67+AB67+AD67+AF67+AH67+AJ67+AL67+AN67+AP67+AR67+AT67+AV67+AX67+AZ67+BB67+BD67+BF67+BH67+BJ67+BL67+BN67+BP67+BR67+BT67+BV67+BX67+BZ67+CB67+CF276 -> 311458 | P67: 311458 | AQ67: 311458
A68: 3 | B68: 46029 | C68: Returns Cost | D68: =F68-E68 -> 0 | E68: =G68+I68+CC277+K68+M68+O68+Q68+S68+U68+W68+Y68+AA68+AC68+AE68+AG68+AI68+AK68+AM68+AO68+AQ68+AS68+AU68+AW68+AY68+BA68+BC68+BE68+BG68+BI68+BK68+BM68+BO68+BQ68+BS68+BU68+BW68+BY68+CA68+CE277 -> 145650 | F68: =H68+J68+L68+CD277+N68+P68+R68+T68+V68+X68+Z68+AB68+AD68+AF68+AH68+AJ68+AL68+AN68+AP68+AR68+AT68+AV68+AX68+AZ68+BB68+BD68+BF68+BH68+BJ68+BL68+BN68+BP68+BR68+BT68+BV68+BX68+BZ68+CB68+CF277 -> 145650 | N68: 145650 | AS68: 145650
A69: 4 | B69: 46029 | C69: Cost | D69: =F69-E69 -> 0 | E69: =G69+I69+CC278+K69+M69+O69+Q69+S69+U69+W69+Y69+AA69+AC69+AE69+AG69+AI69+AK69+AM69+AO69+AQ69+AS69+AU69+AW69+AY69+BA69+BC69+BE69+BG69+BI69+BK69+BM69+BO69+BQ69+BS69+BU69+BW69+BY69+CA69+CE278 -> 325400 | F69: =H69+J69+L69+CD278+N69+P69+R69+T69+V69+X69+Z69+AB69+AD69+AF69+AH69+AJ69+AL69+AN69+AP69+AR69+AT69+AV69+AX69+AZ69+BB69+BD69+BF69+BH69+BJ69+BL69+BN69+BP69+BR69+BT69+BV69+BX69+BZ69+CB69+CF278 -> 325400 | M69: 325400 | AT69: 325400
A70: 5 | B70: 46029 | C70: Shipping | D70: =F70-E70 -> 0 | E70: =G70+I70+CC279+K70+M70+O70+Q70+S70+U70+W70+Y70+AA70+AC70+AE70+AG70+AI70+AK70+AM70+AO70+AQ70+AS70+AU70+AW70+AY70+BA70+BC70+BE70+BG70+BI70+BK70+BM70+BO70+BQ70+BS70+BU70+BW70+BY70+CA70+CE279 -> 3465 | F70: =H70+J70+L70+CD279+N70+P70+R70+T70+V70+X70+Z70+AB70+AD70+AF70+AH70+AJ70+AL70+AN70+AP70+AR70+AT70+AV70+AX70+AZ70+BB70+BD70+BF70+BH70+BJ70+BL70+BN70+BP70+BR70+BT70+BV70+BX70+BZ70+CB70+CF279 -> 3465 | G70: 3465 | AN70: 3465
A71: 6 | B71: 46029 | C71: Pickup | D71: =F71-E71 -> 0 | E71: =G71+I71+CC280+K71+M71+O71+Q71+S71+U71+W71+Y71+AA71+AC71+AE71+AG71+AI71+AK71+AM71+AO71+AQ71+AS71+AU71+AW71+AY71+BA71+BC71+BE71+BG71+BI71+BK71+BM71+BO71+BQ71+BS71+BU71+BW71+BY71+CA71+CE280 -> 377727 | F71: =H71+J71+L71+CD280+N71+P71+R71+T71+V71+X71+Z71+AB71+AD71+AF71+AH71+AJ71+AL71+AN71+AP71+AR71+AT71+AV71+AX71+AZ71+BB71+BD71+BF71+BH71+BJ71+BL71+BN71+BP71+BR71+BT71+BV71+BX71+BZ71+CB71+CF280 -> 377727 | AK71: 377727 | AR71: 377727
A72: 7 | B72: 46029 | C72: Receving | D72: =F72-E72 -> 0 | E72: =G72+I72+CC281+K72+M72+O72+Q72+S72+U72+W72+Y72+AA72+AC72+AE72+AG72+AI72+AK72+AM72+AO72+AQ72+AS72+AU72+AW72+AY72+BA72+BC72+BE72+BG72+BI72+BK72+BM72+BO72+BQ72+BS72+BU72+BW72+BY72+CA72+CE281 -> 239267 | F72: =H72+J72+L72+CD281+N72+P72+R72+T72+V72+X72+Z72+AB72+AD72+AF72+AH72+AJ72+AL72+AN72+AP72+AR72+AT72+AV72+AX72+AZ72+BB72+BD72+BF72+BH72+BJ72+BL72+BN72+BP72+BR72+BT72+BV72+BX72+BZ72+CB72+CF281 -> 239267 | H72: 57496 | J72: 25748 | L72: 7650 | R72: 35350 | T72: 35398 | V72: 8500 | AQ72: 239267 | BV72: 69125
A73: 8 | B73: 46029 | C73: Refund | D73: =F73-E73 -> 0 | E73: =G73+I73+CC283+K73+M73+O73+Q73+S73+U73+W73+Y73+AA73+AC73+AE73+AG73+AI73+AK73+AM73+AO73+AQ73+AS73+AU73+AW73+AY73+BA73+BC73+BE73+BG73+BI73+BK73+BM73+BO73+BQ73+BS73+BU73+BW73+BY73+CA73+CE283 -> 0 | F73: =H73+J73+L73+CD283+N73+P73+R73+T73+V73+X73+Z73+AB73+AD73+AF73+AH73+AJ73+AL73+AN73+AP73+AR73+AT73+AV73+AX73+AZ73+BB73+BD73+BF73+BH73+BJ73+BL73+BN73+BP73+BR73+BT73+BV73+BX73+BZ73+CB73+CF283 -> 0
A74: 9 | B74: 46029 | C74: inventory | D74: =F74-E74 -> 0 | E74: =G74+I74+CC284+K74+M74+O74+Q74+S74+U74+W74+Y74+AA74+AC74+AE74+AG74+AI74+AK74+AM74+AO74+AQ74+AS74+AU74+AW74+AY74+BA74+BC74+BE74+BG74+BI74+BK74+BM74+BO74+BQ74+BS74+BU74+BW74+BY74+CA74+CE284 -> 0 | F74: =H74+J74+L74+CD284+N74+P74+R74+T74+V74+X74+Z74+AB74+AD74+AF74+AH74+AJ74+AL74+AN74+AP74+AR74+AT74+AV74+AX74+AZ74+BB74+BD74+BF74+BH74+BJ74+BL74+BN74+BP74+BR74+BT74+BV74+BX74+BZ74+CB74+CF284 -> 0
A75: 1 | B75: 46030 | C75: Sales | D75: =F75-E75 -> 0 | E75: =G75+I75+CC284+K75+M75+O75+Q75+S75+U75+W75+Y75+AA75+AC75+AE75+AG75+AI75+AK75+AM75+AO75+AQ75+AS75+AU75+AW75+AY75+BA75+BC75+BE75+BG75+BI75+BK75+BM75+BO75+BQ75+BS75+BU75+BW75+BY75+CA75+CE284 -> 382974 | F75: =H75+J75+L75+CD284+N75+P75+R75+T75+V75+X75+Z75+AB75+AD75+AF75+AH75+AJ75+AL75+AN75+AP75+AR75+AT75+AV75+AX75+AZ75+BB75+BD75+BF75+BH75+BJ75+BL75+BN75+BP75+BR75+BT75+BV75+BX75+BZ75+CB75+CF284 -> 382974 | O75: 356437 | AK75: 26537 | AL75: 356437 | AX75: 26537
A76: 2 | B76: 46030 | C76: Returns | D76: =F76-E76 -> 0 | E76: =G76+I76+CC285+K76+M76+O76+Q76+S76+U76+W76+Y76+AA76+AC76+AE76+AG76+AI76+AK76+AM76+AO76+AQ76+AS76+AU76+AW76+AY76+BA76+BC76+BE76+BG76+BI76+BK76+BM76+BO76+BQ76+BS76+BU76+BW76+BY76+CA76+CE285 -> 127717 | F76: =H76+J76+L76+CD285+N76+P76+R76+T76+V76+X76+Z76+AB76+AD76+AF76+AH76+AJ76+AL76+AN76+AP76+AR76+AT76+AV76+AX76+AZ76+BB76+BD76+BF76+BH76+BJ76+BL76+BN76+BP76+BR76+BT76+BV76+BX76+BZ76+CB76+CF285 -> 127717 | P76: 127717 | AQ76: 127717
A77: 3 | B77: 46030 | C77: Returns Cost | D77: =F77-E77 -> 0 | E77: =G77+I77+CC286+K77+M77+O77+Q77+S77+U77+W77+Y77+AA77+AC77+AE77+AG77+AI77+AK77+AM77+AO77+AQ77+AS77+AU77+AW77+AY77+BA77+BC77+BE77+BG77+BI77+BK77+BM77+BO77+BQ77+BS77+BU77+BW77+BY77+CA77+CE286 -> 74200 | F77: =H77+J77+L77+CD286+N77+P77+R77+T77+V77+X77+Z77+AB77+AD77+AF77+AH77+AJ77+AL77+AN77+AP77+AR77+AT77+AV77+AX77+AZ77+BB77+BD77+BF77+BH77+BJ77+BL77+BN77+BP77+BR77+BT77+BV77+BX77+BZ77+CB77+CF286 -> 74200 | N77: 74200 | AS77: 74200
A78: 4 | B78: 46030 | C78: Cost | D78: =F78-E78 -> 0 | E78: =G78+I78+CC283+K78+M78+O78+Q78+S78+U78+W78+Y78+AA78+AC78+AE78+AG78+AI78+AK78+AM78+AO78+AQ78+AS78+AU78+AW78+AY78+BA78+BC78+BE78+BG78+BI78+BK78+BM78+BO78+BQ78+BS78+BU78+BW78+BY78+CA78+CE283 -> 162250 | F78: =H78+J78+L78+CD283+N78+P78+R78+T78+V78+X78+Z78+AB78+AD78+AF78+AH78+AJ78+AL78+AN78+AP78+AR78+AT78+AV78+AX78+AZ78+BB78+BD78+BF78+BH78+BJ78+BL78+BN78+BP78+BR78+BT78+BV78+BX78+BZ78+CB78+CF283 -> 162250 | M78: 162250 | AT78: 162250
A79: 5 | B79: 46030 | C79: Shipping | D79: =F79-E79 -> 0 | E79: =G79+I79+CC284+K79+M79+O79+Q79+S79+U79+W79+Y79+AA79+AC79+AE79+AG79+AI79+AK79+AM79+AO79+AQ79+AS79+AU79+AW79+AY79+BA79+BC79+BE79+BG79+BI79+BK79+BM79+BO79+BQ79+BS79+BU79+BW79+BY79+CA79+CE284 -> 2180 | F79: =H79+J79+L79+CD284+N79+P79+R79+T79+V79+X79+Z79+AB79+AD79+AF79+AH79+AJ79+AL79+AN79+AP79+AR79+AT79+AV79+AX79+AZ79+BB79+BD79+BF79+BH79+BJ79+BL79+BN79+BP79+BR79+BT79+BV79+BX79+BZ79+CB79+CF284 -> 2180 | G79: 2180 | AN79: 2180
A80: 6 | B80: 46030 | C80: Pickup | D80: =F80-E80 -> 0 | E80: =G80+I80+CC285+K80+M80+O80+Q80+S80+U80+W80+Y80+AA80+AC80+AE80+AG80+AI80+AK80+AM80+AO80+AQ80+AS80+AU80+AW80+AY80+BA80+BC80+BE80+BG80+BI80+BK80+BM80+BO80+BQ80+BS80+BU80+BW80+BY80+CA80+CE285 -> 374869 | F80: =H80+J80+L80+CD285+N80+P80+R80+T80+V80+X80+Z80+AB80+AD80+AF80+AH80+AJ80+AL80+AN80+AP80+AR80+AT80+AV80+AX80+AZ80+BB80+BD80+BF80+BH80+BJ80+BL80+BN80+BP80+BR80+BT80+BV80+BX80+BZ80+CB80+CF285 -> 374869 | AK80: 374869 | AR80: 374869
A81: 7 | B81: 46030 | C81: Receving | D81: =F81-E81 -> 0 | E81: =G81+I81+CC286+K81+M81+O81+Q81+S81+U81+W81+Y81+AA81+AC81+AE81+AG81+AI81+AK81+AM81+AO81+AQ81+AS81+AU81+AW81+AY81+BA81+BC81+BE81+BG81+BI81+BK81+BM81+BO81+BQ81+BS81+BU81+BW81+BY81+CA81+CE286 -> 148186 | F81: =H81+J81+L81+CD286+N81+P81+R81+T81+V81+X81+Z81+AB81+AD81+AF81+AH81+AJ81+AL81+AN81+AP81+AR81+AT81+AV81+AX81+AZ81+BB81+BD81+BF81+BH81+BJ81+BL81+BN81+BP81+BR81+BT81+BV81+BX81+BZ81+CB81+CF286 -> 148186 | H81: 47998 | R81: 44214 | AQ81: 148186 | BT81: 22999 | BV81: 32975
A82: 8 | B82: 46030 | C82: Refund | D82: =F82-E82 -> 0 | E82: =G82+I82+CC287+K82+M82+O82+Q82+S82+U82+W82+Y82+AA82+AC82+AE82+AG82+AI82+AK82+AM82+AO82+AQ82+AS82+AU82+AW82+AY82+BA82+BC82+BE82+BG82+BI82+BK82+BM82+BO82+BQ82+BS82+BU82+BW82+BY82+CA82+CE287 -> 0 | F82: =H82+J82+L82+CD287+N82+P82+R82+T82+V82+X82+Z82+AB82+AD82+AF82+AH82+AJ82+AL82+AN82+AP82+AR82+AT82+AV82+AX82+AZ82+BB82+BD82+BF82+BH82+BJ82+BL82+BN82+BP82+BR82+BT82+BV82+BX82+BZ82+CB82+CF287 -> 0
A83: 9 | B83: 46030 | C83: inventory | D83: =F83-E83 -> 0 | E83: =G83+I83+CC291+K83+M83+O83+Q83+S83+U83+W83+Y83+AA83+AC83+AE83+AG83+AI83+AK83+AM83+AO83+AQ83+AS83+AU83+AW83+AY83+BA83+BC83+BE83+BG83+BI83+BK83+BM83+BO83+BQ83+BS83+BU83+BW83+BY83+CA83+CE291 -> 0 | F83: =H83+J83+L83+CD291+N83+P83+R83+T83+V83+X83+Z83+AB83+AD83+AF83+AH83+AJ83+AL83+AN83+AP83+AR83+AT83+AV83+AX83+AZ83+BB83+BD83+BF83+BH83+BJ83+BL83+BN83+BP83+BR83+BT83+BV83+BX83+BZ83+CB83+CF291 -> 0
A84: 1 | B84: 46031 | C84: Sales | D84: =F84-E84 -> 0 | E84: =G84+I84+CC292+K84+M84+O84+Q84+S84+U84+W84+Y84+AA84+AC84+AE84+AG84+AI84+AK84+AM84+AO84+AQ84+AS84+AU84+AW84+AY84+BA84+BC84+BE84+BG84+BI84+BK84+BM84+BO84+BQ84+BS84+BU84+BW84+BY84+CA84+CE292 -> 348097 | F84: =H84+J84+L84+CD292+N84+P84+R84+T84+V84+X84+Z84+AB84+AD84+AF84+AH84+AJ84+AL84+AN84+AP84+AR84+AT84+AV84+AX84+AZ84+BB84+BD84+BF84+BH84+BJ84+BL84+BN84+BP84+BR84+BT84+BV84+BX84+BZ84+CB84+CF292 -> 348097 | O84: 315737 | AK84: 32360 | AL84: 315737 | AX84: 32360
A85: 2 | B85: 46031 | C85: Returns | D85: =F85-E85 -> 0 | E85: =G85+I85+CC293+K85+M85+O85+Q85+S85+U85+W85+Y85+AA85+AC85+AE85+AG85+AI85+AK85+AM85+AO85+AQ85+AS85+AU85+AW85+AY85+BA85+BC85+BE85+BG85+BI85+BK85+BM85+BO85+BQ85+BS85+BU85+BW85+BY85+CA85+CE293 -> 0 | F85: =H85+J85+L85+CD293+N85+P85+R85+T85+V85+X85+Z85+AB85+AD85+AF85+AH85+AJ85+AL85+AN85+AP85+AR85+AT85+AV85+AX85+AZ85+BB85+BD85+BF85+BH85+BJ85+BL85+BN85+BP85+BR85+BT85+BV85+BX85+BZ85+CB85+CF293 -> 0
A86: 3 | B86: 46031 | C86: Returns Cost | D86: =F86-E86 -> 0 | E86: =G86+I86+CC294+K86+M86+O86+Q86+S86+U86+W86+Y86+AA86+AC86+AE86+AG86+AI86+AK86+AM86+AO86+AQ86+AS86+AU86+AW86+AY86+BA86+BC86+BE86+BG86+BI86+BK86+BM86+BO86+BQ86+BS86+BU86+BW86+BY86+CA86+CE294 -> 0 | F86: =H86+J86+L86+CD294+N86+P86+R86+T86+V86+X86+Z86+AB86+AD86+AF86+AH86+AJ86+AL86+AN86+AP86+AR86+AT86+AV86+AX86+AZ86+BB86+BD86+BF86+BH86+BJ86+BL86+BN86+BP86+BR86+BT86+BV86+BX86+BZ86+CB86+CF294 -> 0
A87: 4 | B87: 46031 | C87: Cost | D87: =F87-E87 -> 0 | E87: =G87+I87+CC294+K87+M87+O87+Q87+S87+U87+W87+Y87+AA87+AC87+AE87+AG87+AI87+AK87+AM87+AO87+AQ87+AS87+AU87+AW87+AY87+BA87+BC87+BE87+BG87+BI87+BK87+BM87+BO87+BQ87+BS87+BU87+BW87+BY87+CA87+CE294 -> 127700 | F87: =H87+J87+L87+CD294+N87+P87+R87+T87+V87+X87+Z87+AB87+AD87+AF87+AH87+AJ87+AL87+AN87+AP87+AR87+AT87+AV87+AX87+AZ87+BB87+BD87+BF87+BH87+BJ87+BL87+BN87+BP87+BR87+BT87+BV87+BX87+BZ87+CB87+CF294 -> 127700 | M87: 127700 | AT87: 127700
A88: 5 | B88: 46031 | C88: Shipping | D88: =F88-E88 -> 0 | E88: =G88+I88+CC293+K88+M88+O88+Q88+S88+U88+W88+Y88+AA88+AC88+AE88+AG88+AI88+AK88+AM88+AO88+AQ88+AS88+AU88+AW88+AY88+BA88+BC88+BE88+BG88+BI88+BK88+BM88+BO88+BQ88+BS88+BU88+BW88+BY88+CA88+CE293 -> 0 | F88: =H88+J88+L88+CD293+N88+P88+R88+T88+V88+X88+Z88+AB88+AD88+AF88+AH88+AJ88+AL88+AN88+AP88+AR88+AT88+AV88+AX88+AZ88+BB88+BD88+BF88+BH88+BJ88+BL88+BN88+BP88+BR88+BT88+BV88+BX88+BZ88+CB88+CF293 -> 0
A89: 6 | B89: 46031 | C89: Pickup | D89: =F89-E89 -> 0 | E89: =G89+I89+CC294+K89+M89+O89+Q89+S89+U89+W89+Y89+AA89+AC89+AE89+AG89+AI89+AK89+AM89+AO89+AQ89+AS89+AU89+AW89+AY89+BA89+BC89+BE89+BG89+BI89+BK89+BM89+BO89+BQ89+BS89+BU89+BW89+BY89+CA89+CE294 -> 0 | F89: =H89+J89+L89+CD294+N89+P89+R89+T89+V89+X89+Z89+AB89+AD89+AF89+AH89+AJ89+AL89+AN89+AP89+AR89+AT89+AV89+AX89+AZ89+BB89+BD89+BF89+BH89+BJ89+BL89+BN89+BP89+BR89+BT89+BV89+BX89+BZ89+CB89+CF294 -> 0
A90: 7 | B90: 46031 | C90: Receving | D90: =F90-E90 -> 0 | E90: =G90+I90+CC295+K90+M90+O90+Q90+S90+U90+W90+Y90+AA90+AC90+AE90+AG90+AI90+AK90+AM90+AO90+AQ90+AS90+AU90+AW90+AY90+BA90+BC90+BE90+BG90+BI90+BK90+BM90+BO90+BQ90+BS90+BU90+BW90+BY90+CA90+CE295 -> 64370 | F90: =H90+J90+L90+CD295+N90+P90+R90+T90+V90+X90+Z90+AB90+AD90+AF90+AH90+AJ90+AL90+AN90+AP90+AR90+AT90+AV90+AX90+AZ90+BB90+BD90+BF90+BH90+BJ90+BL90+BN90+BP90+BR90+BT90+BV90+BX90+BZ90+CB90+CF295 -> 64370 | T90: 61895 | AQ90: 64370 | BT90: 2475
A91: 8 | B91: 46031 | C91: Refund | D91: =F91-E91 -> 0 | E91: =G91+I91+CC296+K91+M91+O91+Q91+S91+U91+W91+Y91+AA91+AC91+AE91+AG91+AI91+AK91+AM91+AO91+AQ91+AS91+AU91+AW91+AY91+BA91+BC91+BE91+BG91+BI91+BK91+BM91+BO91+BQ91+BS91+BU91+BW91+BY91+CA91+CE296 -> 0 | F91: =H91+J91+L91+CD296+N91+P91+R91+T91+V91+X91+Z91+AB91+AD91+AF91+AH91+AJ91+AL91+AN91+AP91+AR91+AT91+AV91+AX91+AZ91+BB91+BD91+BF91+BH91+BJ91+BL91+BN91+BP91+BR91+BT91+BV91+BX91+BZ91+CB91+CF296 -> 0
A92: 9 | B92: 46031 | C92: inventory | D92: =F92-E92 -> 0 | E92: =G92+I92+CC302+K92+M92+O92+Q92+S92+U92+W92+Y92+AA92+AC92+AE92+AG92+AI92+AK92+AM92+AO92+AQ92+AS92+AU92+AW92+AY92+BA92+BC92+BE92+BG92+BI92+BK92+BM92+BO92+BQ92+BS92+BU92+BW92+BY92+CA92+CE302 -> 0 | F92: =H92+J92+L92+CD302+N92+P92+R92+T92+V92+X92+Z92+AB92+AD92+AF92+AH92+AJ92+AL92+AN92+AP92+AR92+AT92+AV92+AX92+AZ92+BB92+BD92+BF92+BH92+BJ92+BL92+BN92+BP92+BR92+BT92+BV92+BX92+BZ92+CB92+CF302 -> 0
A93: 1 | B93: 46032 | C93: Sales | D93: =F93-E93 -> 0 | E93: =G93+I93+CC303+K93+M93+O93+Q93+S93+U93+W93+Y93+AA93+AC93+AE93+AG93+AI93+AK93+AM93+AO93+AQ93+AS93+AU93+AW93+AY93+BA93+BC93+BE93+BG93+BI93+BK93+BM93+BO93+BQ93+BS93+BU93+BW93+BY93+CA93+CE303 -> 600626 | F93: =H93+J93+L93+CD303+N93+P93+R93+T93+V93+X93+Z93+AB93+AD93+AF93+AH93+AJ93+AL93+AN93+AP93+AR93+AT93+AV93+AX93+AZ93+BB93+BD93+BF93+BH93+BJ93+BL93+BN93+BP93+BR93+BT93+BV93+BX93+BZ93+CB93+CF303 -> 600626 | O93: 565999 | AK93: 34627 | AL93: 565999 | AX93: 34627
A94: 2 | B94: 46032 | C94: Returns | D94: =F94-E94 -> 0 | E94: =G94+I94+CC303+K94+M94+O94+Q94+S94+U94+W94+Y94+AA94+AC94+AE94+AG94+AI94+AK94+AM94+AO94+AQ94+AS94+AU94+AW94+AY94+BA94+BC94+BE94+BG94+BI94+BK94+BM94+BO94+BQ94+BS94+BU94+BW94+BY94+CA94+CE303 -> 125646 | F94: =H94+J94+L94+CD303+N94+P94+R94+T94+V94+X94+Z94+AB94+AD94+AF94+AH94+AJ94+AL94+AN94+AP94+AR94+AT94+AV94+AX94+AZ94+BB94+BD94+BF94+BH94+BJ94+BL94+BN94+BP94+BR94+BT94+BV94+BX94+BZ94+CB94+CF303 -> 125646 | P94: 125646 | AQ94: 125646
A95: 3 | B95: 46032 | C95: Returns Cost | D95: =F95-E95 -> 0 | E95: =G95+I95+CC304+K95+M95+O95+Q95+S95+U95+W95+Y95+AA95+AC95+AE95+AG95+AI95+AK95+AM95+AO95+AQ95+AS95+AU95+AW95+AY95+BA95+BC95+BE95+BG95+BI95+BK95+BM95+BO95+BQ95+BS95+BU95+BW95+BY95+CA95+CE304 -> 71050 | F95: =H95+J95+L95+CD304+N95+P95+R95+T95+V95+X95+Z95+AB95+AD95+AF95+AH95+AJ95+AL95+AN95+AP95+AR95+AT95+AV95+AX95+AZ95+BB95+BD95+BF95+BH95+BJ95+BL95+BN95+BP95+BR95+BT95+BV95+BX95+BZ95+CB95+CF304 -> 71050 | N95: 71050 | AS95: 71050
A96: 4 | B96: 46032 | C96: Cost | D96: =F96-E96 -> 0 | E96: =G96+I96+CC305+K96+M96+O96+Q96+S96+U96+W96+Y96+AA96+AC96+AE96+AG96+AI96+AK96+AM96+AO96+AQ96+AS96+AU96+AW96+AY96+BA96+BC96+BE96+BG96+BI96+BK96+BM96+BO96+BQ96+BS96+BU96+BW96+BY96+CA96+CE305 -> 243300 | F96: =H96+J96+L96+CD305+N96+P96+R96+T96+V96+X96+Z96+AB96+AD96+AF96+AH96+AJ96+AL96+AN96+AP96+AR96+AT96+AV96+AX96+AZ96+BB96+BD96+BF96+BH96+BJ96+BL96+BN96+BP96+BR96+BT96+BV96+BX96+BZ96+CB96+CF305 -> 243300 | M96: 243300 | AT96: 243300
A97: 5 | B97: 46032 | C97: Shipping | D97: =F97-E97 -> 0 | E97: =G97+I97+CC306+K97+M97+O97+Q97+S97+U97+W97+Y97+AA97+AC97+AE97+AG97+AI97+AK97+AM97+AO97+AQ97+AS97+AU97+AW97+AY97+BA97+BC97+BE97+BG97+BI97+BK97+BM97+BO97+BQ97+BS97+BU97+BW97+BY97+CA97+CE306 -> 2865 | F97: =H97+J97+L97+CD306+N97+P97+R97+T97+V97+X97+Z97+AB97+AD97+AF97+AH97+AJ97+AL97+AN97+AP97+AR97+AT97+AV97+AX97+AZ97+BB97+BD97+BF97+BH97+BJ97+BL97+BN97+BP97+BR97+BT97+BV97+BX97+BZ97+CB97+CF306 -> 2865 | G97: 2865 | AN97: 2865
A98: 6 | B98: 46032 | C98: Pickup | D98: =F98-E98 -> 0 | E98: =G98+I98+CC307+K98+M98+O98+Q98+S98+U98+W98+Y98+AA98+AC98+AE98+AG98+AI98+AK98+AM98+AO98+AQ98+AS98+AU98+AW98+AY98+BA98+BC98+BE98+BG98+BI98+BK98+BM98+BO98+BQ98+BS98+BU98+BW98+BY98+CA98+CE307 -> 703354 | F98: =H98+J98+L98+CD307+N98+P98+R98+T98+V98+X98+Z98+AB98+AD98+AF98+AH98+AJ98+AL98+AN98+AP98+AR98+AT98+AV98+AX98+AZ98+BB98+BD98+BF98+BH98+BJ98+BL98+BN98+BP98+BR98+BT98+BV98+BX98+BZ98+CB98+CF307 -> 703354 | AK98: 703354 | AR98: 703354
A99: 7 | B99: 46032 | C99: Receving | D99: =F99-E99 -> 0 | E99: =G99+I99+CC313+K99+M99+O99+Q99+S99+U99+W99+Y99+AA99+AC99+AE99+AG99+AI99+AK99+AM99+AO99+AQ99+AS99+AU99+AW99+AY99+BA99+BC99+BE99+BG99+BI99+BK99+BM99+BO99+BQ99+BS99+BU99+BW99+BY99+CA99+CE313 -> 270993 | F99: =H99+J99+L99+CD313+N99+P99+R99+T99+V99+X99+Z99+AB99+AD99+AF99+AH99+AJ99+AL99+AN99+AP99+AR99+AT99+AV99+AX99+AZ99+BB99+BD99+BF99+BH99+BJ99+BL99+BN99+BP99+BR99+BT99+BV99+BX99+BZ99+CB99+CF313 -> 270993 | H99: 79135 | R99: 58164 | T99: 76545 | V99: 7650 | AQ99: 270993 | BV99: 49499
A100: 8 | B100: 46032 | C100: Refund | D100: =F100-E100 -> 0 | E100: =G100+I100+CC314+K100+M100+O100+Q100+S100+U100+W100+Y100+AA100+AC100+AE100+AG100+AI100+AK100+AM100+AO100+AQ100+AS100+AU100+AW100+AY100+BA100+BC100+BE100+BG100+BI100+BK100+BM100+BO100+BQ100+BS100+BU100+BW100+BY100+CA100+CE314 -> 10898 | F100: =H100+J100+L100+CD314+N100+P100+R100+T100+V100+X100+Z100+AB100+AD100+AF100+AH100+AJ100+AL100+AN100+AP100+AR100+AT100+AV100+AX100+AZ100+BB100+BD100+BF100+BH100+BJ100+BL100+BN100+BP100+BR100+BT100+BV100+BX100+BZ100+CB100+CF314 -> 10898 | S100: 5399 | AZ100: 10898 | BS100: 5499
...

Sheet Trial balance
A1: Desscription | B1: Total journal entry | D1: Balance
B2: Credit | C2: Debit | D2: Credit | E2: Debit | H2: IN Come steetment | I2: قائمة الدخل | L2: BaLance Sheet الميزانية
A3: ='American journal voucher'!$G$3 -> Cash | B3: ='American journal voucher'!G5098 -> 5066015 | C3: ='American journal voucher'!H5098 -> 5125814 | D3: =IF(B3>C3,B3-C3,0) -> 0 | E3: =IF(C3>B3,C3-B3,0) -> 59799 | L3: Assets
A4: ='American journal voucher'!$I$3 -> Bank | B4: ='American journal voucher'!I5098 -> 0 | C4: ='American journal voucher'!J5098 -> 388408 | D4: =IF(B4>C4,B4-C4,0) -> 0 | E4: =IF(C4>B4,C4-B4,0) -> 388408 | H4: Sales | I4: =D7 -> 23305332 | L4: Fixed assets | M4: 0
A5: ='American journal voucher'!$K$3 -> Vodafon Cash | B5: ='American journal voucher'!K5098 -> 301199.8 | C5: ='American journal voucher'!L5098 -> 267075 | D5: =IF(B5>C5,B5-C5,0) -> 34124.8 | E5: =IF(C5>B5,C5-B5,0) -> 0 | L5: Cash | M5: =E3 -> 59799
A6: ='American journal voucher'!$M$3 -> Inventory | B6: ='American journal voucher'!M5098 -> 21421165 | C6: ='American journal voucher'!N5098 -> 22508915 | D6: =IF(B6>C6,B6-C6,0) -> 0 | E6: =IF(C6>B6,C6-B6,0) -> 1087750 | H6: ='[2]American journal voucher'!$AW$3 -> Discount | I6: =E24 -> 5121874.9 | L6: BANK | M6: =E4 -> 388408
A7: ='American journal voucher'!$O$3 -> Sales | B7: ='American journal voucher'!O5098 -> 47869388 | C7: ='American journal voucher'!P5098 -> 24564056 | D7: =IF(B7>C7,B7-C7,0) -> 23305332 | E7: =IF(C7>B7,C7-B7,0) -> 0 | H7: Refund | I7: =E25 -> 944383 | L7: V.F
A8: ='American journal voucher'!$Q$3 -> Instapay 2 | B8: ='American journal voucher'!Q5098 -> 480856 | C8: ='American journal voucher'!R5098 -> 3635524 | D8: =IF(B8>C8,B8-C8,0) -> 0 | E8: =IF(C8>B8,C8-B8,0) -> 3154668 | L8: INVENTORY | M8: =E6 -> 1087750
A9: ='American journal voucher'!$S$3 -> Paymob | B9: ='American journal voucher'!S5098 -> 205991 | C9: ='American journal voucher'!T5098 -> 3515583 | D9: =IF(B9>C9,B9-C9,0) -> 0 | E9: =IF(C9>B9,C9-B9,0) -> 3309592 | H9: net sales | I9: =I4-I6-I7 -> 17239074 | L9: INSTAPAY | M9: =E36 -> 2696489
A10: ='American journal voucher'!$U$3 -> Value | B10: ='American journal voucher'!U5098 -> 204775 | C10: ='American journal voucher'!V5098 -> 2037083 | D10: =IF(B10>C10,B10-C10,0) -> 0 | E10: =IF(C10>B10,C10-B10,0) -> 1832308 | H10: Cost | I10: =E22 -> 8786830 | L10: INSTAPAY 2 | M10: =E8 -> 3154668
A11: ='American journal voucher'!$W$3 -> Gift Card | B11: ='American journal voucher'!W5098 -> 20372 | C11: ='American journal voucher'!X5098 -> 75267 | D11: =IF(B11>C11,B11-C11,0) -> 0 | E11: =IF(C11>B11,C11-B11,0) -> 54895 | L11: Paymob | M11: =E9 -> 3309592
A12: ='American journal voucher'!$Y$3 -> Share holder's | B12: ='American journal voucher'!Y5098 -> 5585853 | C12: ='American journal voucher'!Z5098 -> 6000 | D12: =IF(B12>C12,B12-C12,0) -> 5579853 | E12: =IF(C12>B12,C12-B12,0) -> 0 | H12: Gross Profit | I12: =I9-I10 -> 8452243.9 | L12: Value | M12: =E10 -> 1832308
A13: ='American journal voucher'!$AA$3 -> Depreciation | B13: ='American journal voucher'!AA5098 -> 0 | C13: ='American journal voucher'!AB5098 -> 0 | D13: =IF(B13>C13,B13-C13,0) -> 0 | E13: =IF(C13>B13,C13-B13,0) -> 0 | L13: Gift Card | M13: =E11 -> 54895
A14: ='American journal voucher'!$AC$3 -> Capital | B14: ='American journal voucher'!AC5098 -> 0 | C14: ='American journal voucher'!AD5098 -> 0 | D14: =IF(B14>C14,B14-C14,0) -> 0 | E14: =IF(C14>B14,C14-B14,0) -> 0 | H14: EX | L14: SYMPL | M14: =E36 -> 2696489
A15: ='American journal voucher'!$AE$3 -> Retained earning | B15: ='American journal voucher'!AE5098 -> 0 | C15: ='American journal voucher'!AF5098 -> 0 | D15: =IF(B15>C15,B15-C15,0) -> 0 | E15: =IF(C15>B15,C15-B15,0) -> 0 | H15: Administrative Expenses | I15: =E20 -> 1170982 | L15: Opreation
A16: ='American journal voucher'!$AG$3 -> Prepared Expenses | B16: ='American journal voucher'!AG5098 -> 0 | C16: ='American journal voucher'!AH5098 -> 0 | D16: =IF(B16>C16,B16-C16,0) -> 0 | E16: =IF(C16>B16,C16-B16,0) -> 0 | H16: Shipping | I16: =E19 -> 326070
A17: ='American journal voucher'!$AI$3 -> Fixed assets | B17: ='American journal voucher'!AI5098 -> 0 | C17: ='American journal voucher'!AJ5098 -> 0 | D17: =IF(B17>C17,B17-C17,0) -> 0 | E17: =IF(C17>B17,C17-B17,0) -> 0 | H17: Markting | I17: =E27 -> 5863798.8 | L17: Tootal Assets
A18: ='American journal voucher'!$AK$3 -> Opreation | B18: ='American journal voucher'!AK5098 -> 52353184 | C18: ='American journal voucher'!AL5098 -> 47869388 | D18: =IF(B18>C18,B18-C18,0) -> 4483795.9 | E18: =IF(C18>B18,C18-B18,0) -> 0 | H18: Tootal Ex | I18: =I15+I16+I17 -> 7360850.8 | L18: Capital
A19: ='American journal voucher'!$AM$3 -> Shipping | B19: ='American journal voucher'!AM5098 -> 0 | C19: ='American journal voucher'!AN5098 -> 326070 | D19: =IF(B19>C19,B19-C19,0) -> 0 | E19: =IF(C19>B19,C19-B19,0) -> 326070 | L19: Share holders
A20: ='American journal voucher'!$AO$3 -> Administrative Expenses | B20: ='American journal voucher'!AO5098 -> 670 | C20: ='American journal voucher'!AP5098 -> 1171652 | D20: =IF(B20>C20,B20-C20,0) -> 0 | E20: =IF(C20>B20,C20-B20,0) -> 1170982 | L20: Purchasing
A21: ='American journal voucher'!$AQ$3 -> Advance to employees | B21: ='American journal voucher'!AQ5098 -> 43140847 | C21: ='American journal voucher'!AR5098 -> 47231309 | D21: =IF(B21>C21,B21-C21,0) -> 0 | E21: =IF(C21>B21,C21-B21,0) -> 4090461.8 | L21: P&l
A22: ='American journal voucher'!$AS$3 -> Cost | B22: ='American journal voucher'!AS5098 -> 12634335 | C22: ='American journal voucher'!AT5098 -> 21421165 | D22: =IF(B22>C22,B22-C22,0) -> 0 | E22: =IF(C22>B22,C22-B22,0) -> 8786830 | H22: NET Profit | I22: =I12-I18 -> 1091393.1 | L22: Advance to employees
A23: ='American journal voucher'!$AU$3 -> Purchasing | B23: ='American journal voucher'!AU5098 -> 9874580 | C23: ='American journal voucher'!AV5098 -> 3634400 | D23: =IF(B23>C23,B23-C23,0) -> 6240180 | E23: =IF(C23>B23,C23-B23,0) -> 0 | L23: Net Profit
A24: ='American journal voucher'!$AW$3 -> Discount | B24: ='American journal voucher'!AW5098 -> 0 | C24: ='American journal voucher'!AX5098 -> 5121874.9 | D24: =IF(B24>C24,B24-C24,0) -> 0 | E24: =IF(C24>B24,C24-B24,0) -> 5121874.9 | L24: Tootal Assets
A25: ='American journal voucher'!$AY$3 -> Refund | B25: ='American journal voucher'!AY5098 -> 0 | C25: ='American journal voucher'!AZ5098 -> 944383 | D25: =IF(B25>C25,B25-C25,0) -> 0 | E25: =IF(C25>B25,C25-B25,0) -> 944383
A26: ='American journal voucher'!$BA$3 -> Suppliers | B26: ='American journal voucher'!BA5098 -> 0 | C26: ='American journal voucher'!BB5098 -> 0 | D26: =IF(B26>C26,B26-C26,0) -> 0 | E26: =IF(C26>B26,C26-B26,0) -> 0
A27: ='American journal voucher'!$BC$3 -> Markting | B27: ='American journal voucher'!BC5098 -> 0 | C27: ='American journal voucher'!BD5098 -> 5863798.8 | D27: =IF(B27>C27,B27-C27,0) -> 0 | E27: =IF(C27>B27,C27-B27,0) -> 5863798.8
A28: ='American journal voucher'!$BE$3 -> Bank Masr | B28: ='American journal voucher'!BE5098 -> 0 | C28: ='American journal voucher'!BF5098 -> 0 | D28: =IF(B28>C28,B28-C28,0) -> 0 | E28: =IF(C28>B28,C28-B28,0) -> 0
A29: ='American journal voucher'!$BG$3 -> Bank interest | B29: ='American journal voucher'!BG5098 -> 0 | C29: ='American journal voucher'!BH5098 -> 0 | D29: =IF(B29>C29,B29-C29,0) -> 0 | E29: =IF(C29>B29,C29-B29,0) -> 0
A30: ='American journal voucher'!$BI$3 -> other Ep | B30: ='American journal voucher'!BI5098 -> 0 | C30: ='American journal voucher'!BJ5098 -> 0 | D30: =IF(B30>C30,B30-C30,0) -> 0 | E30: =IF(C30>B30,C30-B30,0) -> 0
A31: ='American journal voucher'!$BK$3 -> Bank interest cr | B31: ='American journal voucher'!BK5098 -> 0 | C31: ='American journal voucher'!BL5098 -> 0 | D31: =IF(B31>C31,B31-C31,0) -> 0 | E31: =IF(C31>B31,C31-B31,0) -> 0
A32: ='American journal voucher'!$BM$3 -> p&l | B32: ='American journal voucher'!BM5098 -> 0 | C32: ='American journal voucher'!BN5098 -> 0 | D32: =IF(B32>C32,B32-C32,0) -> 0 | E32: =IF(C32>B32,C32-B32,0) -> 0
A33: ='American journal voucher'!$BO$3 -> deposits revenue | B33: ='American journal voucher'!BO5098 -> 0 | C33: ='American journal voucher'!BP5098 -> 0 | D33: =IF(B33>C33,B33-C33,0) -> 0 | E33: =IF(C33>B33,C33-B33,0) -> 0
A34: ='American journal voucher'!$BQ$3 -> سلف | B34: ='American journal voucher'!BQ5098 -> 11700 | C34: ='American journal voucher'!BR5098 -> 11000 | D34: =IF(B34>C34,B34-C34,0) -> 700 | E34: =IF(C34>B34,C34-B34,0) -> 0
A35: ='American journal voucher'!$BS$3 -> SYMPL | B35: ='American journal voucher'!BS5098 -> 112242 | C35: ='American journal voucher'!BT5098 -> 867918 | D35: =IF(B35>C35,B35-C35,0) -> 0 | E35: =IF(C35>B35,C35-B35,0) -> 755676
A36: ='American journal voucher'!$BU$3 -> INSTAPAY | B36: ='American journal voucher'!BU5098 -> 0 | C36: ='American journal voucher'!BV5098 -> 2696489 | D36: =IF(B36>C36,B36-C36,0) -> 0 | E36: =IF(C36>B36,C36-B36,0) -> 2696489
A37: ='American journal voucher'!$BW$3 -> 0 | B37: ='American journal voucher'!BW5098 -> 0 | C37: ='American journal voucher'!BX5098 -> 0 | D37: =IF(B37>C37,B37-C37,0) -> 0 | E37: =IF(C37>B37,C37-B37,0) -> 0
A38: ='American journal voucher'!$BY$3 -> 0 | B38: ='American journal voucher'!BY5098 -> 0 | C38: ='American journal voucher'!BZ5098 -> 0 | D38: =IF(B38>C38,B38-C38,0) -> 0 | E38: =IF(C38>B38,C38-B38,0) -> 0
A39: ='American journal voucher'!$CA$3 -> 0 | B39: ='American journal voucher'!CA5098 -> 0 | C39: ='American journal voucher'!CB5098 -> 0 | D39: =IF(B39>C39,B39-C39,0) -> 0 | E39: =IF(C39>B39,C39-B39,0) -> 0
A40: ='American journal voucher'!$CC$3 -> 0 | B40: ='American journal voucher'!CC5106 -> 0 | C40: ='American journal voucher'!CD5106 -> 0 | D40: =IF(B40>C40,B40-C40,0) -> 0 | E40: =IF(C40>B40,C40-B40,0) -> 0
A41: ='American journal voucher'!$CE$3 -> 0 | B41: ='American journal voucher'!CE5106 -> 0 | C41: ='American journal voucher'!CF5106 -> 0 | D41: =IF(B41>C41,B41-C41,0) -> 0 | E41: =IF(C41>B41,C41-B41,0) -> 0
A42: Total | B42: =SUM(B3:B40) -> 1.9928317e+08 | C42: =SUM(C3:C40) -> 1.9928317e+08 | D42: =SUM(D3:D41) -> 39643986 | E42: =SUM(E3:E41) -> 39643986
D43: =D42-E42 -> 0
B44: =B42-C42 -> 0
